{"version":2,"kind":"Article","sha256":"88ca9a9990ec7adb9b44ca8e2388120558e595e1cc628283e35e634438164921","slug":"index","location":"/README.md","dependencies":[],"frontmatter":{"title":"Snow Cookbook","content_includes_title":true,"authors":[{"nameParsed":{"literal":"The SnowPit Community","given":"The SnowPit","family":"Community"},"name":"The SnowPit Community","id":"contributors-myst-generated-uid-0"}],"open_access":true,"license":{"content":{"id":"CC-BY-4.0","url":"https://creativecommons.org/licenses/by/4.0/","name":"Creative Commons Attribution 4.0 International","free":true,"CC":true},"code":{"id":"Apache-2.0","url":"https://opensource.org/licenses/Apache-2.0","name":"Apache License 2.0","free":true,"osi":true}},"github":"https://github.com/SnowEx/snow-cookbook","copyright":"2025","affiliations":[{"id":"UAlbany","name":"University at Albany (SUNY)","department":"Atmospheric and Environmental Sciences","url":"https://www.albany.edu/daes"},{"id":"CISL","name":"NSF National Center for Atmospheric Research","department":"Computational and Information Systems Lab","url":"https://www.cisl.ucar.edu"},{"id":"Unidata","name":"NSF Unidata","url":"https://www.unidata.ucar.edu"},{"id":"Argonne","name":"Argonne National Laboratory","department":"Environmental Science Division","url":"https://www.anl.gov/evs"},{"id":"CarbonPlan","name":"CarbonPlan","url":"https://carbonplan.org"},{"id":"NVIDIA","name":"NVIDIA Corporation","url":"https://www.nvidia.com/"}],"edit_url":"https://github.com/SnowEx/snow-cookbook/blob/HEAD/README.md","thumbnail":"/snow-cookbook/_preview/7/build/3a5b2698b5d21d107a57901ba13beff9.png","exports":[{"format":"md","filename":"README.md","url":"/snow-cookbook/_preview/7/build/README-932b02f2ff806010eb15ceb457795ab5.md"}]},"mdast":{"type":"root","children":[{"type":"block","children":[{"type":"paragraph","position":{"start":{"line":1,"column":1},"end":{"line":2,"column":1}},"children":[{"type":"image","url":"/snow-cookbook/_preview/7/build/3a5b2698b5d21d107a57901ba13beff9.png","alt":"thumbnail","width":300,"key":"co42oKh24j","urlSource":"https://snow.nasa.gov/sites/default/files/inline-images/snow-banner.png"}],"key":"dnvXFJ6sZZ"},{"type":"heading","depth":1,"position":{"start":{"line":4,"column":1},"end":{"line":4,"column":1}},"children":[{"type":"text","value":"Snow Cookbook","position":{"start":{"line":4,"column":1},"end":{"line":4,"column":1}},"key":"ztqvg7rU7x"}],"identifier":"snow-cookbook","label":"Snow Cookbook","html_id":"snow-cookbook","implicit":true,"key":"ckg8Lygrb7"},{"type":"paragraph","position":{"start":{"line":6,"column":1},"end":{"line":8,"column":1}},"children":[{"type":"link","url":"https://github.com/SnowEx/snow-cookbook/actions/workflows/nightly-build.yaml","position":{"start":{"line":6,"column":1},"end":{"line":6,"column":1}},"children":[{"type":"image","url":"/snow-cookbook/_preview/7/build/4cc2a537d809f1498f9cf53aebc6e56a.svg","alt":"nightly-build","position":{"start":{"line":6,"column":1},"end":{"line":6,"column":1}},"key":"vGgAY4JTRb","urlSource":"https://github.com/SnowEx/snow-cookbook/actions/workflows/nightly-build.yaml/badge.svg"}],"urlSource":"https://github.com/SnowEx/snow-cookbook/actions/workflows/nightly-build.yaml","error":true,"key":"KkBSGrwBS7"},{"type":"text","value":"\n","position":{"start":{"line":6,"column":1},"end":{"line":6,"column":1}},"key":"ljSYbD100a"},{"type":"link","url":"https://binder.projectpythia.org/v2/gh/snowEx/snow-cookbook/main?labpath=notebooks","position":{"start":{"line":6,"column":1},"end":{"line":6,"column":1}},"children":[{"type":"image","url":"/snow-cookbook/_preview/7/build/31e3f387ea168934ca949c27e9927ea4.svg","alt":"Binder","position":{"start":{"line":6,"column":1},"end":{"line":6,"column":1}},"key":"AC8JKWHyFL","urlSource":"https://binder.projectpythia.org/badge_logo.svg"}],"urlSource":"https://binder.projectpythia.org/v2/gh/snowEx/snow-cookbook/main?labpath=notebooks","key":"qoptViglbw"},{"type":"text","value":"\n","position":{"start":{"line":6,"column":1},"end":{"line":6,"column":1}},"key":"B01rrCgCtF"},{"type":"cite","url":"https://doi.org/10.5281/zenodo.14205550","position":{"start":{"line":6,"column":1},"end":{"line":6,"column":1}},"children":[{"type":"image","url":"/snow-cookbook/_preview/7/build/238a71ffc6f9c4a30d93ba3dbf149dd0.svg","alt":"DOI","position":{"start":{"line":6,"column":1},"end":{"line":6,"column":1}},"key":"VlfEOCCT8y","urlSource":"https://zenodo.org/badge/DOI/10.5281/zenodo.14205550.svg"}],"kind":"narrative","label":"https://doi.org/10.5281/zenodo.14205550","identifier":"https://doi.org/10.5281/zenodo.14205550","enumerator":"1","key":"d5vRtdEUzP"}],"key":"omx1iR5mcK"},{"type":"paragraph","position":{"start":{"line":11,"column":1},"end":{"line":16,"column":1}},"children":[{"type":"text","value":"This Project Pythia Cookbook is a compilation of tutorials and training\nmaterials in support of the NASA snow reserach community. Some tutorials\ncome from the 2020 to 2024 SnowEx Hackweek program hosted at the UW eScience\nInstitute. Other materials are drawn from the NASA Goddard “SnowPit” Science\nTask Group or STG. The purpose of the tutorials is to help people with data\naccess and to demonstrate a variety of disciplinary use cases.","position":{"start":{"line":11,"column":1},"end":{"line":11,"column":1}},"key":"PapyFoDjnr"}],"key":"YlhIkSTBtm"},{"type":"heading","depth":2,"position":{"start":{"line":18,"column":1},"end":{"line":18,"column":1}},"children":[{"type":"text","value":"Motivation","position":{"start":{"line":18,"column":1},"end":{"line":18,"column":1}},"key":"n5FgbxDIKo"}],"identifier":"motivation","label":"Motivation","html_id":"motivation","implicit":true,"key":"hh2sXVR4qh"},{"type":"paragraph","position":{"start":{"line":20,"column":1},"end":{"line":24,"column":1}},"children":[{"type":"text","value":"There are numerous data products and methods for accessing and analyzing\nsnow observations. These include field, airborne, and satellite missions.\nThe goal of these tutorials is to streamline data access, reduce duplication\nof effort and build an open science community around snow research\ndatasets, algorithms and software.","position":{"start":{"line":20,"column":1},"end":{"line":20,"column":1}},"key":"krlsTqiEgi"}],"key":"R2r8PcdnDf"},{"type":"heading","depth":2,"position":{"start":{"line":26,"column":1},"end":{"line":26,"column":1}},"children":[{"type":"text","value":"Authors","position":{"start":{"line":26,"column":1},"end":{"line":26,"column":1}},"key":"A5Q8NQyTn1"}],"identifier":"authors","label":"Authors","html_id":"authors","implicit":true,"key":"XgqE194cGR"},{"type":"paragraph","position":{"start":{"line":28,"column":1},"end":{"line":30,"column":1}},"children":[{"type":"link","url":"@zachghiaccio","position":{"start":{"line":28,"column":1},"end":{"line":28,"column":1}},"children":[{"type":"text","value":"Zach Fair","position":{"start":{"line":28,"column":1},"end":{"line":28,"column":1}},"key":"jCOK5LQts0"}],"urlSource":"@zachghiaccio","key":"BKakakCj1Y"},{"type":"text","value":"\n","position":{"start":{"line":28,"column":1},"end":{"line":28,"column":1}},"key":"adao7XoD3Z"},{"type":"link","url":"@aaarendt","position":{"start":{"line":28,"column":1},"end":{"line":28,"column":1}},"children":[{"type":"text","value":"Anthony Arendt","position":{"start":{"line":28,"column":1},"end":{"line":28,"column":1}},"key":"coBNU4S0RE"}],"urlSource":"@aaarendt","key":"fVZ2ExmDh2"},{"type":"text","value":",\n","position":{"start":{"line":28,"column":1},"end":{"line":28,"column":1}},"key":"GrBcTkMXUk"},{"type":"link","url":"@markweldensmith","position":{"start":{"line":28,"column":1},"end":{"line":28,"column":1}},"children":[{"type":"text","value":"Mark Welden-Smith","position":{"start":{"line":28,"column":1},"end":{"line":28,"column":1}},"key":"HgReL1a73X"}],"urlSource":"@markweldensmith","key":"xS6EcxwyMv"}],"key":"JlJxE4ZKj9"},{"type":"paragraph","position":{"start":{"line":32,"column":1},"end":{"line":32,"column":1}},"children":[{"type":"text","value":"more to be added","position":{"start":{"line":32,"column":1},"end":{"line":32,"column":1}},"key":"n0hXnN1ZDe"}],"key":"Ito19loIDP"},{"type":"heading","depth":3,"position":{"start":{"line":34,"column":1},"end":{"line":34,"column":1}},"children":[{"type":"text","value":"Contributors","position":{"start":{"line":34,"column":1},"end":{"line":34,"column":1}},"key":"nK7CBAMreO"}],"identifier":"contributors","label":"Contributors","html_id":"contributors","implicit":true,"key":"eNpUMUVQkH"},{"type":"link","url":"https://github.com/SnowEx/snow-cookbook/graphs/contributors","children":[{"type":"image","url":"/snow-cookbook/_preview/7/build/f4fe8598128e362eb05a572bddb0624e.svg","key":"psorEzzJyR","urlSource":"https://contrib.rocks/image?repo=SnowEx/snow-cookbook"}],"urlSource":"https://github.com/SnowEx/snow-cookbook/graphs/contributors","error":true,"key":"TBR85Fh7VK"},{"type":"heading","depth":2,"position":{"start":{"line":40,"column":1},"end":{"line":40,"column":1}},"children":[{"type":"text","value":"Structure","position":{"start":{"line":40,"column":1},"end":{"line":40,"column":1}},"key":"qeubwPRdgp"}],"identifier":"structure","label":"Structure","html_id":"structure","implicit":true,"key":"qMGMBlRfgk"},{"type":"paragraph","position":{"start":{"line":42,"column":1},"end":{"line":43,"column":1}},"children":[{"type":"text","value":"This cookbook is broken up into two main sections - “Foundations”\nand “Example Workflows.”","position":{"start":{"line":42,"column":1},"end":{"line":42,"column":1}},"key":"E33UtxUce7"}],"key":"fHyvPscJdS"},{"type":"heading","depth":3,"position":{"start":{"line":45,"column":1},"end":{"line":45,"column":1}},"children":[{"type":"text","value":"Section 1: Foundations","position":{"start":{"line":45,"column":1},"end":{"line":45,"column":1}},"key":"PQsrEcjwP5"}],"identifier":"section-1-foundations","label":"Section 1: Foundations","html_id":"section-1-foundations","implicit":true,"key":"WtqSVPAMpo"},{"type":"list","ordered":false,"spread":false,"position":{"start":{"line":47,"column":1},"end":{"line":48,"column":1}},"children":[{"type":"listItem","spread":true,"position":{"start":{"line":47,"column":1},"end":{"line":48,"column":1}},"children":[{"type":"text","value":"TBD","position":{"start":{"line":47,"column":1},"end":{"line":47,"column":1}},"key":"jr7h3qhTdO"}],"key":"OgZx2TRyn2"}],"key":"W0zpdkg6Sa"},{"type":"heading","depth":3,"position":{"start":{"line":49,"column":1},"end":{"line":49,"column":1}},"children":[{"type":"text","value":"Section 2: Example Workflows for Specific Disciplines","position":{"start":{"line":49,"column":1},"end":{"line":49,"column":1}},"key":"SpPNGYMsOn"}],"identifier":"section-2-example-workflows-for-specific-disciplines","label":"Section 2: Example Workflows for Specific Disciplines","html_id":"section-2-example-workflows-for-specific-disciplines","implicit":true,"key":"S0rmOGeKt3"},{"type":"list","ordered":false,"spread":false,"position":{"start":{"line":51,"column":1},"end":{"line":52,"column":1}},"children":[{"type":"listItem","spread":true,"position":{"start":{"line":51,"column":1},"end":{"line":52,"column":1}},"children":[{"type":"text","value":"TBD","position":{"start":{"line":51,"column":1},"end":{"line":51,"column":1}},"key":"Mu710VhWiu"}],"key":"PAiRMUQzPD"}],"key":"GAgThCr12L"},{"type":"heading","depth":2,"position":{"start":{"line":53,"column":1},"end":{"line":53,"column":1}},"children":[{"type":"text","value":"Running the Notebooks","position":{"start":{"line":53,"column":1},"end":{"line":53,"column":1}},"key":"BLJqggzSv0"}],"identifier":"running-the-notebooks","label":"Running the Notebooks","html_id":"running-the-notebooks","implicit":true,"key":"Y29b0YNdoy"},{"type":"paragraph","position":{"start":{"line":55,"column":1},"end":{"line":56,"column":1}},"children":[{"type":"text","value":"You can either run the notebook using\n","position":{"start":{"line":55,"column":1},"end":{"line":55,"column":1}},"key":"iRBQsWlaMk"},{"type":"link","url":"https://binder.projectpythia.org/","position":{"start":{"line":55,"column":1},"end":{"line":55,"column":1}},"children":[{"type":"text","value":"Binder","position":{"start":{"line":55,"column":1},"end":{"line":55,"column":1}},"key":"ZX0nJrg0Xv"}],"urlSource":"https://binder.projectpythia.org/","key":"sznYzNAXlU"},{"type":"text","value":" or on your local machine.","position":{"start":{"line":55,"column":1},"end":{"line":55,"column":1}},"key":"hGdFPz4YeL"}],"key":"WSpY4JTG6p"},{"type":"heading","depth":3,"position":{"start":{"line":58,"column":1},"end":{"line":58,"column":1}},"children":[{"type":"text","value":"Running on Binder","position":{"start":{"line":58,"column":1},"end":{"line":58,"column":1}},"key":"SF9uTRUHMF"}],"identifier":"running-on-binder","label":"Running on Binder","html_id":"running-on-binder","implicit":true,"key":"hWnWMknQ8C"},{"type":"paragraph","position":{"start":{"line":60,"column":1},"end":{"line":73,"column":1}},"children":[{"type":"text","value":"The simplest way to interact with a Jupyter Notebook is through\n","position":{"start":{"line":60,"column":1},"end":{"line":60,"column":1}},"key":"jTVrlYIUDq"},{"type":"link","url":"https://binder.projectpythia.org/","position":{"start":{"line":60,"column":1},"end":{"line":60,"column":1}},"children":[{"type":"text","value":"Binder","position":{"start":{"line":60,"column":1},"end":{"line":60,"column":1}},"key":"xsL75zF1Ga"}],"urlSource":"https://binder.projectpythia.org/","key":"Ui84OfboK0"},{"type":"text","value":", which enables the execution of a\n","position":{"start":{"line":60,"column":1},"end":{"line":60,"column":1}},"key":"rpghlrMK2U"},{"type":"link","url":"https://jupyterbook.org","position":{"start":{"line":60,"column":1},"end":{"line":60,"column":1}},"children":[{"type":"text","value":"Jupyter Book","position":{"start":{"line":60,"column":1},"end":{"line":60,"column":1}},"key":"TTMdfeA6Cl"}],"urlSource":"https://jupyterbook.org","key":"xcs6vBhB4O"},{"type":"text","value":" in the cloud. The details of\nhow this works are not important for now. All you need to know is how to launch\na Pythia Cookbooks chapter via Binder. Simply navigate your mouse to\nthe top right corner of the book chapter you are viewing and click\non the rocket ship icon, (see figure below), and be sure to select\n“launch Binder”. After a moment you should be presented with a\nnotebook that you can interact with. I.e. you’ll be able to execute\nand even change the example programs. You’ll see that the code cells\nhave no output at first, until you execute them by pressing\n","position":{"start":{"line":60,"column":1},"end":{"line":60,"column":1}},"key":"JlOV936IJV"},{"type":"keyboard","children":[{"type":"text","value":"Shift","key":"xqBdelmrY9"}],"key":"Fdw2U0AvR3"},{"type":"text","value":"+","position":{"start":{"line":60,"column":1},"end":{"line":60,"column":1}},"key":"tZ4QZkwFBd"},{"type":"keyboard","children":[{"type":"text","value":"Enter","key":"PfZW3uVvGC"}],"key":"MgryucTPBc"},{"type":"text","value":". Complete details on how to interact with\na live Jupyter notebook are described in ","position":{"start":{"line":60,"column":1},"end":{"line":60,"column":1}},"key":"mI95E82004"},{"type":"link","url":"https://foundations.projectpythia.org/foundations/getting-started-jupyter.html","position":{"start":{"line":60,"column":1},"end":{"line":60,"column":1}},"children":[{"type":"text","value":"Getting Started with\nJupyter","position":{"start":{"line":60,"column":1},"end":{"line":60,"column":1}},"key":"g4GoKDxM97"}],"urlSource":"https://foundations.projectpythia.org/foundations/getting-started-jupyter.html","key":"zIT4sVSuyD"},{"type":"text","value":".","position":{"start":{"line":60,"column":1},"end":{"line":60,"column":1}},"key":"KcvRRUBaa4"}],"key":"n4RVZedPj4"},{"type":"paragraph","position":{"start":{"line":75,"column":1},"end":{"line":77,"column":1}},"children":[{"type":"text","value":"Note, not all Cookbook chapters are executable. If you do not see\nthe rocket ship icon, such as on this page, you are not viewing an\nexecutable book chapter.","position":{"start":{"line":75,"column":1},"end":{"line":75,"column":1}},"key":"gBn2rzjjHc"}],"key":"ayScH62hFF"},{"type":"heading","depth":3,"position":{"start":{"line":80,"column":1},"end":{"line":80,"column":1}},"children":[{"type":"text","value":"Running on Your Own Machine","position":{"start":{"line":80,"column":1},"end":{"line":80,"column":1}},"key":"JzRSVylUC5"}],"identifier":"running-on-your-own-machine","label":"Running on Your Own Machine","html_id":"running-on-your-own-machine","implicit":true,"key":"oLDYD1kVU3"},{"type":"paragraph","position":{"start":{"line":82,"column":1},"end":{"line":83,"column":1}},"children":[{"type":"text","value":"If you are interested in running this material locally on your computer,\nyou will need to follow this workflow:","position":{"start":{"line":82,"column":1},"end":{"line":82,"column":1}},"key":"nnfp46yvqa"}],"key":"x1NwPb7IB7"},{"type":"list","ordered":true,"start":1,"spread":false,"position":{"start":{"line":86,"column":1},"end":{"line":105,"column":1}},"children":[{"type":"listItem","spread":true,"position":{"start":{"line":86,"column":1},"end":{"line":91,"column":1}},"children":[{"type":"paragraph","position":{"start":{"line":86,"column":1},"end":{"line":86,"column":1}},"children":[{"type":"text","value":"Clone the ","position":{"start":{"line":86,"column":1},"end":{"line":86,"column":1}},"key":"kvVrgAEySO"},{"type":"inlineCode","value":"https://github.com/ProjectPythia/snow-cookbook","position":{"start":{"line":86,"column":1},"end":{"line":86,"column":1}},"key":"WnApbFmY5d"},{"type":"text","value":" repository:","position":{"start":{"line":86,"column":1},"end":{"line":86,"column":1}},"key":"UHBCsSnf60"}],"key":"u6V8K3ezdS"},{"type":"code","lang":"bash","value":" git clone https://github.com/ProjectPythia/snow-cookbook.git","position":{"start":{"line":88,"column":1},"end":{"line":90,"column":1}},"key":"xVVzHVfqQu"}],"key":"KExvyRLsap"},{"type":"listItem","spread":true,"position":{"start":{"line":92,"column":1},"end":{"line":95,"column":1}},"children":[{"type":"paragraph","position":{"start":{"line":92,"column":1},"end":{"line":92,"column":1}},"children":[{"type":"text","value":"Move into the ","position":{"start":{"line":92,"column":1},"end":{"line":92,"column":1}},"key":"PS1Bt0FS9i"},{"type":"inlineCode","value":"snow-cookbook","position":{"start":{"line":92,"column":1},"end":{"line":92,"column":1}},"key":"GDY0dUkPN1"},{"type":"text","value":" directory","position":{"start":{"line":92,"column":1},"end":{"line":92,"column":1}},"key":"LhaGSEmvyi"}],"key":"zd4mmrEGwL"},{"type":"code","lang":"bash","value":"cd snow-cookbook","position":{"start":{"line":93,"column":1},"end":{"line":95,"column":1}},"key":"NAQL6kjMNi"}],"key":"Koi6B6NG1x"},{"type":"listItem","spread":true,"position":{"start":{"line":96,"column":1},"end":{"line":100,"column":1}},"children":[{"type":"paragraph","position":{"start":{"line":96,"column":1},"end":{"line":96,"column":1}},"children":[{"type":"text","value":"Create and activate your conda environment from the ","position":{"start":{"line":96,"column":1},"end":{"line":96,"column":1}},"key":"WUHzVQYKZu"},{"type":"inlineCode","value":"environment.yml","position":{"start":{"line":96,"column":1},"end":{"line":96,"column":1}},"key":"Wb3gUyOGf2"},{"type":"text","value":" file","position":{"start":{"line":96,"column":1},"end":{"line":96,"column":1}},"key":"og5iLNBIcR"}],"key":"LxVy7ax0Jb"},{"type":"code","lang":"bash","value":"conda env create -f environment.yml\nconda activate snow-cookbook","position":{"start":{"line":97,"column":1},"end":{"line":100,"column":1}},"key":"KgYrnybHcN"}],"key":"JxMaBJTmx5"},{"type":"listItem","spread":true,"position":{"start":{"line":101,"column":1},"end":{"line":105,"column":1}},"children":[{"type":"paragraph","position":{"start":{"line":101,"column":1},"end":{"line":101,"column":1}},"children":[{"type":"text","value":"Move into the ","position":{"start":{"line":101,"column":1},"end":{"line":101,"column":1}},"key":"cEOaTXi4tM"},{"type":"inlineCode","value":"notebooks","position":{"start":{"line":101,"column":1},"end":{"line":101,"column":1}},"key":"LuWfvKMaq0"},{"type":"text","value":" directory and start up Jupyterlab","position":{"start":{"line":101,"column":1},"end":{"line":101,"column":1}},"key":"UclTqGzYPD"}],"key":"gDrali7Lyj"},{"type":"code","lang":"bash","value":"cd notebooks/\njupyter lab","position":{"start":{"line":102,"column":1},"end":{"line":105,"column":1}},"key":"wbG1mb2MD1"}],"key":"dNhL1Re1ie"}],"key":"oNMNKhkIc3"}],"key":"ESAgZdgp6C"}],"key":"DOaiim6XN7"},"references":{"cite":{"order":["https://doi.org/10.5281/zenodo.14205550"],"data":{"https://doi.org/10.5281/zenodo.14205550":{"label":"https://doi.org/10.5281/zenodo.14205550","enumerator":"1","doi":"10.5281/ZENODO.14205550","html":"Joachim Meyer, Micah Johnson, Megan Mason, dylan boyd, Scott Henderson, agentrrb, Jessica Scheick, Micah Sandusky, Brent Wilder, Ibrahim O Alabi, Mikala Beig, & Naomi Alterman. (2024). <i>snowex-hackweek/website-2024: hackweek-2024</i>. Zenodo. <a target=\"_blank\" rel=\"noreferrer\" href=\"https://doi.org/10.5281/ZENODO.14205550\">10.5281/ZENODO.14205550</a>","url":"https://doi.org/10.5281/ZENODO.14205550"}}}},"footer":{"navigation":{"next":{"title":"How to Cite This Cookbook","url":"/notebooks/how-to-cite","group":"Preamble"}}},"domain":"http://localhost:3000"}