{"version":2,"kind":"Notebook","sha256":"57b4c3565a30efd8a6183c26e8411c1d43c2c39264246cc1217cee419238ead1","slug":"notebooks.snowex-data-overview","location":"/notebooks/snowex_data_overview.ipynb","dependencies":[],"frontmatter":{"title":"Field Campaigns Overview","content_includes_title":true,"kernelspec":{"name":"python3","display_name":"Python 3 (ipykernel)","language":"python"},"authors":[{"nameParsed":{"literal":"The SnowPit Community","given":"The SnowPit","family":"Community"},"name":"The SnowPit Community","id":"contributors-myst-generated-uid-0"}],"open_access":true,"license":{"content":{"id":"CC-BY-4.0","url":"https://creativecommons.org/licenses/by/4.0/","name":"Creative Commons Attribution 4.0 International","free":true,"CC":true},"code":{"id":"Apache-2.0","url":"https://opensource.org/licenses/Apache-2.0","name":"Apache License 2.0","free":true,"osi":true}},"github":"https://github.com/SnowEx/snow-cookbook","copyright":"2025","affiliations":[{"id":"UAlbany","name":"University at Albany (SUNY)","department":"Atmospheric and Environmental Sciences","url":"https://www.albany.edu/daes"},{"id":"CISL","name":"NSF National Center for Atmospheric Research","department":"Computational and Information Systems Lab","url":"https://www.cisl.ucar.edu"},{"id":"Unidata","name":"NSF Unidata","url":"https://www.unidata.ucar.edu"},{"id":"Argonne","name":"Argonne National Laboratory","department":"Environmental Science Division","url":"https://www.anl.gov/evs"},{"id":"CarbonPlan","name":"CarbonPlan","url":"https://carbonplan.org"},{"id":"NVIDIA","name":"NVIDIA Corporation","url":"https://www.nvidia.com/"}],"numbering":{"title":{"offset":1}},"edit_url":"https://github.com/SnowEx/snow-cookbook/blob/HEAD/notebooks/snowex_data_overview.ipynb","exports":[{"format":"ipynb","filename":"snowex_data_overview.ipynb","url":"/snow-cookbook/_preview/9/build/snowex_data_overview-7621954b36af05ae578a8201ca3290a8.ipynb"}]},"widgets":{},"mdast":{"type":"root","children":[{"type":"block","kind":"notebook-content","children":[{"type":"image","url":"/myst_assets_folder./content/01_banner.png","position":{"start":{"line":1,"column":1},"end":{"line":1,"column":1}},"key":"jw6Pd2fGZp"}],"key":"EAE91GgTzj"},{"type":"block","kind":"notebook-content","children":[{"type":"heading","depth":1,"position":{"start":{"line":1,"column":1},"end":{"line":1,"column":1}},"children":[{"type":"text","value":"Field Campaigns Overview","position":{"start":{"line":1,"column":1},"end":{"line":1,"column":1}},"key":"rEteTd9T5j"}],"identifier":"field-campaigns-overview","label":"Field Campaigns Overview","html_id":"field-campaigns-overview","implicit":true,"key":"BQNHeyjRS7"},{"type":"paragraph","position":{"start":{"line":2,"column":1},"end":{"line":2,"column":1}},"children":[{"type":"text","value":"(5 minutes)","position":{"start":{"line":2,"column":1},"end":{"line":2,"column":1}},"key":"ZahzGu3lry"}],"key":"CM2uIzlQoT"},{"type":"paragraph","position":{"start":{"line":4,"column":1},"end":{"line":4,"column":1}},"children":[{"type":"text","value":"By: ","position":{"start":{"line":4,"column":1},"end":{"line":4,"column":1}},"key":"aRKowmksqD"},{"type":"strong","position":{"start":{"line":4,"column":1},"end":{"line":4,"column":1}},"children":[{"type":"text","value":"Megan Mason","position":{"start":{"line":4,"column":1},"end":{"line":4,"column":1}},"key":"SfImhlqtQQ"}],"key":"UG8yOZEwfi"},{"type":"text","value":" (NASA Goddard / SSAI) ","position":{"start":{"line":4,"column":1},"end":{"line":4,"column":1}},"key":"Kra53vtHoN"},{"type":"link","url":"mailto:megan.a.mason@nasa.gov","position":{"start":{"line":4,"column":1},"end":{"line":4,"column":1}},"children":[{"type":"text","value":"megan​.a​.mason@nasa​.gov","position":{"start":{"line":4,"column":1},"end":{"line":4,"column":1}},"key":"TD2S0NpDQ5"}],"urlSource":"mailto:megan.a.mason@nasa.gov","key":"eOYrk3zqeW"}],"key":"LtpEW0hj6a"},{"type":"paragraph","position":{"start":{"line":6,"column":1},"end":{"line":6,"column":1}},"children":[{"type":"text","value":"Support by:  ","position":{"start":{"line":6,"column":1},"end":{"line":6,"column":1}},"key":"g4yS245Yv1"},{"type":"strong","position":{"start":{"line":6,"column":1},"end":{"line":6,"column":1}},"children":[{"type":"text","value":"Carrie Vuyovich","position":{"start":{"line":6,"column":1},"end":{"line":6,"column":1}},"key":"dqBDVPZocy"}],"key":"k4ltRDTRHb"},{"type":"text","value":" (NASA Goddard), ","position":{"start":{"line":6,"column":1},"end":{"line":6,"column":1}},"key":"jhjnH5GktO"},{"type":"strong","position":{"start":{"line":6,"column":1},"end":{"line":6,"column":1}},"children":[{"type":"text","value":"Hans-Peter Marshall","position":{"start":{"line":6,"column":1},"end":{"line":6,"column":1}},"key":"M9i4qyvwMB"}],"key":"ddl7PDmInO"},{"type":"text","value":" (Boise State), ","position":{"start":{"line":6,"column":1},"end":{"line":6,"column":1}},"key":"r91mMUSrWH"},{"type":"strong","position":{"start":{"line":6,"column":1},"end":{"line":6,"column":1}},"children":[{"type":"text","value":"Svetlana Stuefer","position":{"start":{"line":6,"column":1},"end":{"line":6,"column":1}},"key":"rLiS1Pf1hA"}],"key":"jlM2tLHf2E"},{"type":"text","value":" (University of Alaska Fairbanks)","position":{"start":{"line":6,"column":1},"end":{"line":6,"column":1}},"key":"Kn5esygTB3"}],"key":"cv8qL8aIQx"}],"key":"x7YlCWoTIw"},{"type":"block","kind":"notebook-content","children":[{"type":"admonition","children":[{"type":"admonitionTitle","children":[{"type":"text","value":"Learning Objectives","position":{"start":{"line":1,"column":1},"end":{"line":1,"column":1}},"key":"LPNn4o4Frc"}],"key":"x2QMkrTHHM"},{"type":"list","ordered":false,"spread":false,"position":{"start":{"line":2,"column":1},"end":{"line":3,"column":1}},"children":[{"type":"listItem","spread":true,"position":{"start":{"line":2,"column":1},"end":{"line":2,"column":1}},"children":[{"type":"text","value":"Visual overview of the NASA SnowEx field campaigns","position":{"start":{"line":2,"column":1},"end":{"line":2,"column":1}},"key":"aC34fHIRjo"}],"key":"tAJZyaNgIP"},{"type":"listItem","spread":true,"position":{"start":{"line":3,"column":1},"end":{"line":3,"column":1}},"children":[{"type":"text","value":"Get a sense for the extent of data coverage","position":{"start":{"line":3,"column":1},"end":{"line":3,"column":1}},"key":"HzOkVLfanV"}],"key":"sulR3EmBlw"}],"key":"y97X9Gn3yU"}],"key":"E4T2ZsBF8a"}],"key":"qxyZPJGvlj"},{"type":"block","kind":"notebook-content","children":[{"type":"image","url":"/myst_assets_folder./content/01_teaser.png","position":{"start":{"line":1,"column":1},"end":{"line":1,"column":1}},"key":"ppjHHVZFFv"}],"key":"Pb1uaTTttZ"},{"type":"block","kind":"notebook-content","children":[{"type":"heading","depth":2,"position":{"start":{"line":1,"column":1},"end":{"line":1,"column":1}},"children":[{"type":"text","value":"Data Coverage","position":{"start":{"line":1,"column":1},"end":{"line":1,"column":1}},"key":"KYBe2vwPRh"}],"identifier":"data-coverage","label":"Data Coverage","html_id":"data-coverage","implicit":true,"key":"VQUpGcrl4A"},{"type":"paragraph","position":{"start":{"line":2,"column":1},"end":{"line":2,"column":1}},"children":[{"type":"text","value":"Each year we build upon our efforts to further investigate snow remote sensing science gaps identified in the NASA SnowEx Science Plan ","position":{"start":{"line":2,"column":1},"end":{"line":2,"column":1}},"key":"nT2A6U6j7U"},{"type":"link","url":"https://snow.nasa.gov/sites/default/files/SnowEx_Science_Plan_v1.6.pdf","position":{"start":{"line":2,"column":1},"end":{"line":2,"column":1}},"children":[{"type":"text","value":"(Durand et al., 2016)","position":{"start":{"line":2,"column":1},"end":{"line":2,"column":1}},"key":"LJmbuIZ4ou"}],"urlSource":"https://snow.nasa.gov/sites/default/files/SnowEx_Science_Plan_v1.6.pdf","key":"AZslgWA9mC"},{"type":"text","value":". The summary table lists the focus for each campaign by year and type. There are two different campaign types (IOP vs. TS); both result in the same types of measurements and data products. Depending on the  research application it may not matter at all which you choose to work with, or even combine! The important thing to grasp is the difference in spatial and temporal extent of the campaign periods. If the sampling protocols or data products change over time, it is for the sake of improvement. When possible, we aim to keep things consistent to continue to build a legacy data set.","position":{"start":{"line":2,"column":1},"end":{"line":2,"column":1}},"key":"vnx1OqCegp"}],"key":"OrclTPVe7z"}],"key":"EDeNNVk9Ty"},{"type":"block","kind":"notebook-content","children":[{"type":"table","position":{"start":{"line":1,"column":1},"end":{"line":6,"column":1}},"children":[{"type":"tableRow","position":{"start":{"line":1,"column":1},"end":{"line":1,"column":1}},"children":[{"type":"tableCell","header":true,"align":"left","position":{"start":{"line":1,"column":1},"end":{"line":1,"column":1}},"children":[{"type":"strong","position":{"start":{"line":1,"column":1},"end":{"line":1,"column":1}},"children":[{"type":"text","value":"Year","position":{"start":{"line":1,"column":1},"end":{"line":1,"column":1}},"key":"EBsaI0pZ7M"}],"key":"bq7PJJGQvs"}],"key":"fIFdQa3RZd"},{"type":"tableCell","header":true,"align":"left","position":{"start":{"line":1,"column":1},"end":{"line":1,"column":1}},"children":[{"type":"strong","position":{"start":{"line":1,"column":1},"end":{"line":1,"column":1}},"children":[{"type":"text","value":"Campaign Type","position":{"start":{"line":1,"column":1},"end":{"line":1,"column":1}},"key":"P2RyDAy6p6"}],"key":"o4psPjeDBY"}],"key":"jgUb5LJpv4"},{"type":"tableCell","header":true,"align":"left","position":{"start":{"line":1,"column":1},"end":{"line":1,"column":1}},"children":[{"type":"strong","position":{"start":{"line":1,"column":1},"end":{"line":1,"column":1}},"children":[{"type":"text","value":"Measurement Focus","position":{"start":{"line":1,"column":1},"end":{"line":1,"column":1}},"key":"suJq2kuvnA"}],"key":"PHo0DtYFLj"}],"key":"FYOn1veD2u"}],"key":"NBFGLIGOfO"},{"type":"tableRow","position":{"start":{"line":3,"column":1},"end":{"line":3,"column":1}},"children":[{"type":"tableCell","align":"left","position":{"start":{"line":3,"column":1},"end":{"line":3,"column":1}},"children":[{"type":"text","value":"2017","position":{"start":{"line":3,"column":1},"end":{"line":3,"column":1}},"key":"udXEIs0ic5"}],"key":"qT83LlINSU"},{"type":"tableCell","align":"left","position":{"start":{"line":3,"column":1},"end":{"line":3,"column":1}},"children":[{"type":"text","value":"IOP","position":{"start":{"line":3,"column":1},"end":{"line":3,"column":1}},"key":"NWBVtAChUi"}],"key":"KjNhOWN0w8"},{"type":"tableCell","align":"left","position":{"start":{"line":3,"column":1},"end":{"line":3,"column":1}},"children":[{"type":"text","value":"Colorado, focused on multiple instruments in a forest gradient.","position":{"start":{"line":3,"column":1},"end":{"line":3,"column":1}},"key":"fbX7JjJgkI"}],"key":"ctwdtx9uQM"}],"key":"cu2YFgop9S"},{"type":"tableRow","position":{"start":{"line":4,"column":1},"end":{"line":4,"column":1}},"children":[{"type":"tableCell","align":"left","position":{"start":{"line":4,"column":1},"end":{"line":4,"column":1}},"children":[{"type":"text","value":"2020","position":{"start":{"line":4,"column":1},"end":{"line":4,"column":1}},"key":"yxEm671xHm"}],"key":"iRRjoWQLtT"},{"type":"tableCell","align":"left","position":{"start":{"line":4,"column":1},"end":{"line":4,"column":1}},"children":[{"type":"text","value":"IOP, TS","position":{"start":{"line":4,"column":1},"end":{"line":4,"column":1}},"key":"OClree4JqJ"}],"key":"M72QEiZJ0Q"},{"type":"tableCell","align":"left","position":{"start":{"line":4,"column":1},"end":{"line":4,"column":1}},"children":[{"type":"text","value":"Western U.S focused on Time Series of L-band InSAR, active/passive microwave for SWE and thermal IR for snow surface temp.","position":{"start":{"line":4,"column":1},"end":{"line":4,"column":1}},"key":"huAxqScrww"}],"key":"TMOSint7k0"}],"key":"b8TSoACVCe"},{"type":"tableRow","position":{"start":{"line":5,"column":1},"end":{"line":5,"column":1}},"children":[{"type":"tableCell","align":"left","position":{"start":{"line":5,"column":1},"end":{"line":5,"column":1}},"children":[{"type":"text","value":"2021","position":{"start":{"line":5,"column":1},"end":{"line":5,"column":1}},"key":"N8PV1Xl6a0"}],"key":"EP7YEoTnQT"},{"type":"tableCell","align":"left","position":{"start":{"line":5,"column":1},"end":{"line":5,"column":1}},"children":[{"type":"text","value":"TS","position":{"start":{"line":5,"column":1},"end":{"line":5,"column":1}},"key":"Uzw0NBWCyd"}],"key":"C9hZmOMXCr"},{"type":"tableCell","align":"left","position":{"start":{"line":5,"column":1},"end":{"line":5,"column":1}},"children":[{"type":"text","value":"Western U.S, continued Time Series of L-band InSAR, also addressed prairie & snow albedo questions.","position":{"start":{"line":5,"column":1},"end":{"line":5,"column":1}},"key":"Mtoe9eSiv9"}],"key":"bemBoYWSbK"}],"key":"uItJhkLlFj"},{"type":"tableRow","position":{"start":{"line":6,"column":1},"end":{"line":6,"column":1}},"children":[{"type":"tableCell","align":"left","position":{"start":{"line":6,"column":1},"end":{"line":6,"column":1}},"children":[{"type":"text","value":"2023","position":{"start":{"line":6,"column":1},"end":{"line":6,"column":1}},"key":"ekcjfDhUk8"}],"key":"Cuaegwb3ZQ"},{"type":"tableCell","align":"left","position":{"start":{"line":6,"column":1},"end":{"line":6,"column":1}},"children":[{"type":"text","value":"IOP","position":{"start":{"line":6,"column":1},"end":{"line":6,"column":1}},"key":"R7a4qrM7JA"}],"key":"Dy2CbbcZhQ"},{"type":"tableCell","align":"left","position":{"start":{"line":6,"column":1},"end":{"line":6,"column":1}},"children":[{"type":"text","value":"Alaska Tundra & Boreal forest, focused on addressing SWE/snow depth and albedo objectives.","position":{"start":{"line":6,"column":1},"end":{"line":6,"column":1}},"key":"WfsZQgl6Uv"}],"key":"FhUR84iV0W"}],"key":"Kt6JBfew19"}],"key":"KsK7dnkPKc"},{"type":"paragraph","position":{"start":{"line":9,"column":1},"end":{"line":9,"column":1}},"children":[{"type":"text","value":"*IOP=Intense Observation Period (~2-3 week, daily observations) *; ","position":{"start":{"line":9,"column":1},"end":{"line":9,"column":1}},"key":"ggVHTbWfwS"},{"type":"emphasis","position":{"start":{"line":9,"column":1},"end":{"line":9,"column":1}},"children":[{"type":"text","value":"TS=Time Series (~3-5 month winter, weekly observations)","position":{"start":{"line":9,"column":1},"end":{"line":9,"column":1}},"key":"YpdBApKE5u"}],"key":"RUhGfSggG8"}],"key":"O7GCzXgfAl"},{"type":"thematicBreak","position":{"start":{"line":10,"column":1},"end":{"line":10,"column":1}},"key":"lQwcCNCxdJ"}],"key":"gIZhwpndDt"},{"type":"block","kind":"notebook-content","children":[{"type":"heading","depth":3,"position":{"start":{"line":1,"column":1},"end":{"line":1,"column":1}},"children":[{"type":"text","value":"Where has SnowEx Been?","position":{"start":{"line":1,"column":1},"end":{"line":1,"column":1}},"key":"Gb8QXITyFP"}],"identifier":"where-has-snowex-been","label":"Where has SnowEx Been?","html_id":"where-has-snowex-been","implicit":true,"key":"WSalYesW9F"},{"type":"paragraph","position":{"start":{"line":2,"column":1},"end":{"line":2,"column":1}},"children":[{"type":"text","value":"Campaign efforts are focused on various snow climates in the western United States. SnowEx partnerships and expertise are spread across the U.S and international.","position":{"start":{"line":2,"column":1},"end":{"line":2,"column":1}},"key":"wLZ7wSKazS"}],"key":"aI3QDT2spD"},{"type":"paragraph","position":{"start":{"line":4,"column":1},"end":{"line":5,"column":1}},"children":[{"type":"image","url":"/myst_assets_folder./content/01_snowex-map.png","position":{"start":{"line":4,"column":1},"end":{"line":4,"column":1}},"key":"wPvu8Ty6mT"},{"type":"text","value":"\n","position":{"start":{"line":4,"column":1},"end":{"line":4,"column":1}},"key":"nGJH1k2EfY"},{"type":"strong","position":{"start":{"line":4,"column":1},"end":{"line":4,"column":1}},"children":[{"type":"text","value":"Figure 1.","position":{"start":{"line":4,"column":1},"end":{"line":4,"column":1}},"key":"jzsgRDIrPF"}],"key":"EgNXhHGZEH"},{"type":"text","value":" Map showing the locations of SnowEx field campaign areas (red dot). Base map shows snow classes defined in ","position":{"start":{"line":4,"column":1},"end":{"line":4,"column":1}},"key":"ENrDR58XKF"},{"type":"link","url":"https://journals.ametsoc.org/view/journals/hydr/22/11/JHM-D-21-0070.1.xml","position":{"start":{"line":4,"column":1},"end":{"line":4,"column":1}},"children":[{"type":"text","value":"Sturm and Liston, 2021","position":{"start":{"line":4,"column":1},"end":{"line":4,"column":1}},"key":"aF06NJr2E6"}],"urlSource":"https://journals.ametsoc.org/view/journals/hydr/22/11/JHM-D-21-0070.1.xml","key":"XyVa54jwVj"},{"type":"text","value":". The snow pit images show a representative pit in each of the class types visited by SnowEx.","position":{"start":{"line":4,"column":1},"end":{"line":4,"column":1}},"key":"hpBEzv6Xxj"}],"key":"CxkMf30EpV"}],"key":"iwejdDL6pU"},{"type":"block","kind":"notebook-content","children":[{"type":"paragraph","position":{"start":{"line":1,"column":1},"end":{"line":1,"column":1}},"children":[{"type":"strong","position":{"start":{"line":1,"column":1},"end":{"line":1,"column":1}},"children":[{"type":"text","value":"Table 1. Number of manual depths and snow pits associated with NASA SnowEx measurement periods.","position":{"start":{"line":1,"column":1},"end":{"line":1,"column":1}},"key":"crNLi4hSGo"}],"key":"cMG0unWk0T"}],"key":"q4HASw2qDF"},{"type":"table","position":{"start":{"line":3,"column":1},"end":{"line":8,"column":1}},"children":[{"type":"tableRow","position":{"start":{"line":3,"column":1},"end":{"line":3,"column":1}},"children":[{"type":"tableCell","header":true,"position":{"start":{"line":3,"column":1},"end":{"line":3,"column":1}},"children":[{"type":"strong","position":{"start":{"line":3,"column":1},"end":{"line":3,"column":1}},"children":[{"type":"text","value":"SnowEx","position":{"start":{"line":3,"column":1},"end":{"line":3,"column":1}},"key":"gk02AxkX4G"}],"key":"bLSOIOBifW"}],"key":"teT7ejtRng"},{"type":"tableCell","header":true,"position":{"start":{"line":3,"column":1},"end":{"line":3,"column":1}},"children":[{"type":"strong","position":{"start":{"line":3,"column":1},"end":{"line":3,"column":1}},"children":[{"type":"text","value":"Field Campaign Location","position":{"start":{"line":3,"column":1},"end":{"line":3,"column":1}},"key":"duUKp0uGKh"}],"key":"d6wB0E6ntT"}],"key":"MzvXT7t9c3"},{"type":"tableCell","header":true,"position":{"start":{"line":3,"column":1},"end":{"line":3,"column":1}},"children":[{"type":"strong","position":{"start":{"line":3,"column":1},"end":{"line":3,"column":1}},"children":[{"type":"text","value":"Temporal Coverage","position":{"start":{"line":3,"column":1},"end":{"line":3,"column":1}},"key":"b1rZUrIXxI"}],"key":"VVoWc3k8Ee"}],"key":"zSh7PX5Kvc"},{"type":"tableCell","header":true,"align":"center","position":{"start":{"line":3,"column":1},"end":{"line":3,"column":1}},"children":[{"type":"strong","position":{"start":{"line":3,"column":1},"end":{"line":3,"column":1}},"children":[{"type":"text","value":"Manual Depths","position":{"start":{"line":3,"column":1},"end":{"line":3,"column":1}},"key":"SVG936diT0"}],"key":"T9cUKo3L8v"}],"key":"UuxYV5XJTP"},{"type":"tableCell","header":true,"align":"center","position":{"start":{"line":3,"column":1},"end":{"line":3,"column":1}},"children":[{"type":"strong","position":{"start":{"line":3,"column":1},"end":{"line":3,"column":1}},"children":[{"type":"text","value":"Snow Pits","position":{"start":{"line":3,"column":1},"end":{"line":3,"column":1}},"key":"R3KWPLZFMs"}],"key":"JDWFGF4szQ"}],"key":"MVQ95bcrlZ"}],"key":"kTGdYaYadI"},{"type":"tableRow","position":{"start":{"line":5,"column":1},"end":{"line":5,"column":1}},"children":[{"type":"tableCell","position":{"start":{"line":5,"column":1},"end":{"line":5,"column":1}},"children":[{"type":"strong","position":{"start":{"line":5,"column":1},"end":{"line":5,"column":1}},"children":[{"type":"text","value":"S17","position":{"start":{"line":5,"column":1},"end":{"line":5,"column":1}},"key":"ncpVx0BmFg"}],"key":"gPgcm5jT9l"}],"key":"EUyCQyhMN5"},{"type":"tableCell","position":{"start":{"line":5,"column":1},"end":{"line":5,"column":1}},"children":[{"type":"text","value":"Grand Mesa & Senator Beck Basin, Colorado","position":{"start":{"line":5,"column":1},"end":{"line":5,"column":1}},"key":"bW6gzCTGuS"}],"key":"BkTo4QrDzZ"},{"type":"tableCell","position":{"start":{"line":5,"column":1},"end":{"line":5,"column":1}},"children":[{"type":"text","value":"February 6-25, 2017","position":{"start":{"line":5,"column":1},"end":{"line":5,"column":1}},"key":"jvK2FqQHrr"}],"key":"PXjm6NL2oQ"},{"type":"tableCell","align":"center","position":{"start":{"line":5,"column":1},"end":{"line":5,"column":1}},"children":[{"type":"text","value":"23,432","position":{"start":{"line":5,"column":1},"end":{"line":5,"column":1}},"key":"egA6TPM0FB"}],"key":"ZBtJElg1TH"},{"type":"tableCell","align":"center","position":{"start":{"line":5,"column":1},"end":{"line":5,"column":1}},"children":[{"type":"text","value":"265","position":{"start":{"line":5,"column":1},"end":{"line":5,"column":1}},"key":"dRoWmK7Xs9"}],"key":"OEabe1Ihmf"}],"key":"mgkknUlj0M"},{"type":"tableRow","position":{"start":{"line":6,"column":1},"end":{"line":6,"column":1}},"children":[{"type":"tableCell","position":{"start":{"line":6,"column":1},"end":{"line":6,"column":1}},"children":[{"type":"strong","position":{"start":{"line":6,"column":1},"end":{"line":6,"column":1}},"children":[{"type":"text","value":"S20","position":{"start":{"line":6,"column":1},"end":{"line":6,"column":1}},"key":"K5IzOoHTnQ"}],"key":"keQEQXCFvs"}],"key":"kZ9Kek8THr"},{"type":"tableCell","position":{"start":{"line":6,"column":1},"end":{"line":6,"column":1}},"children":[{"type":"text","value":"Grand Mesa, Colorado","position":{"start":{"line":6,"column":1},"end":{"line":6,"column":1}},"key":"v1hUpbNUAj"},{"type":"break","key":"G92I8LAN1g"},{"type":"text","value":"Western U.S Time Series (13 sites)","position":{"start":{"line":6,"column":1},"end":{"line":6,"column":1}},"key":"DiNQNo2utu"}],"key":"aFE1d6PFVH"},{"type":"tableCell","position":{"start":{"line":6,"column":1},"end":{"line":6,"column":1}},"children":[{"type":"text","value":"November 4-7, 2019","position":{"start":{"line":6,"column":1},"end":{"line":6,"column":1}},"key":"PAylSqEWJa"},{"type":"break","key":"qZvZNVhuKG"},{"type":"text","value":"January 27-February 12, 2020","position":{"start":{"line":6,"column":1},"end":{"line":6,"column":1}},"key":"ANLWCWeyu1"},{"type":"break","key":"LwPDqgijRH"},{"type":"text","value":"October 24-May 20, 2020*","position":{"start":{"line":6,"column":1},"end":{"line":6,"column":1}},"key":"wZ8ZQwYgic"}],"key":"wBnKrOHaqk"},{"type":"tableCell","align":"center","position":{"start":{"line":6,"column":1},"end":{"line":6,"column":1}},"children":[{"type":"text","value":"16,212","position":{"start":{"line":6,"column":1},"end":{"line":6,"column":1}},"key":"YU9S9UP07s"},{"type":"break","key":"el0RgDAj3E"},{"type":"text","value":"37,921","position":{"start":{"line":6,"column":1},"end":{"line":6,"column":1}},"key":"IOY339il5o"},{"type":"break","key":"YU3Uwe8Ucr"},{"type":"text","value":"TBD","position":{"start":{"line":6,"column":1},"end":{"line":6,"column":1}},"key":"QPlHjSnSiP"}],"key":"d75PfMCRw3"},{"type":"tableCell","align":"center","position":{"start":{"line":6,"column":1},"end":{"line":6,"column":1}},"children":[{"type":"text","value":"21","position":{"start":{"line":6,"column":1},"end":{"line":6,"column":1}},"key":"aWQVVFsAUl"},{"type":"break","key":"rqIswnOQhX"},{"type":"text","value":"154","position":{"start":{"line":6,"column":1},"end":{"line":6,"column":1}},"key":"Bsc0NHIWPf"},{"type":"break","key":"l60KB5qqBl"},{"type":"text","value":"454","position":{"start":{"line":6,"column":1},"end":{"line":6,"column":1}},"key":"FVlKuzvjsM"}],"key":"WmgE3yW7Eu"}],"key":"sxqzE0AniS"},{"type":"tableRow","position":{"start":{"line":7,"column":1},"end":{"line":7,"column":1}},"children":[{"type":"tableCell","position":{"start":{"line":7,"column":1},"end":{"line":7,"column":1}},"children":[{"type":"strong","position":{"start":{"line":7,"column":1},"end":{"line":7,"column":1}},"children":[{"type":"text","value":"S21","position":{"start":{"line":7,"column":1},"end":{"line":7,"column":1}},"key":"JovFkgthn3"}],"key":"RXJT6sVHCC"}],"key":"o7aMFQ3421"},{"type":"tableCell","position":{"start":{"line":7,"column":1},"end":{"line":7,"column":1}},"children":[{"type":"text","value":"Western U.S Time Series (7 sites)","position":{"start":{"line":7,"column":1},"end":{"line":7,"column":1}},"key":"RBqfxKxNMw"}],"key":"u53j5TIS6k"},{"type":"tableCell","position":{"start":{"line":7,"column":1},"end":{"line":7,"column":1}},"children":[{"type":"text","value":"November 16-May 27, 2021","position":{"start":{"line":7,"column":1},"end":{"line":7,"column":1}},"key":"GcfBzwl0Or"}],"key":"afegy1aw30"},{"type":"tableCell","align":"center","position":{"start":{"line":7,"column":1},"end":{"line":7,"column":1}},"children":[{"type":"text","value":"12,536","position":{"start":{"line":7,"column":1},"end":{"line":7,"column":1}},"key":"eVJUQrWCQM"}],"key":"yJweJZEY4u"},{"type":"tableCell","align":"center","position":{"start":{"line":7,"column":1},"end":{"line":7,"column":1}},"children":[{"type":"text","value":"247","position":{"start":{"line":7,"column":1},"end":{"line":7,"column":1}},"key":"QrWNv7xyHt"}],"key":"ObGQKUgEnc"}],"key":"RmQILQppbx"},{"type":"tableRow","position":{"start":{"line":8,"column":1},"end":{"line":8,"column":1}},"children":[{"type":"tableCell","position":{"start":{"line":8,"column":1},"end":{"line":8,"column":1}},"children":[{"type":"strong","position":{"start":{"line":8,"column":1},"end":{"line":8,"column":1}},"children":[{"type":"text","value":"S23","position":{"start":{"line":8,"column":1},"end":{"line":8,"column":1}},"key":"xzqp9v4phu"}],"key":"IRPRSNjNzv"}],"key":"LhhFL49JZM"},{"type":"tableCell","position":{"start":{"line":8,"column":1},"end":{"line":8,"column":1}},"children":[{"type":"text","value":"Tundra & Boreal Forest, Alaska (pre-campaign site visit)","position":{"start":{"line":8,"column":1},"end":{"line":8,"column":1}},"key":"LgAkHty7rs"},{"type":"break","key":"mErqBIF7lM"},{"type":"text","value":"Tundra & Boreal Forest, Alaska","position":{"start":{"line":8,"column":1},"end":{"line":8,"column":1}},"key":"zAX1pCii7n"},{"type":"break","key":"KTQSKgO5R7"},{"type":"text","value":"Tundra & Boreal Forest, Alaska","position":{"start":{"line":8,"column":1},"end":{"line":8,"column":1}},"key":"tItLfO9dYF"},{"type":"break","key":"dxif7pMUvt"},{"type":"text","value":"Boreal Forest, Alaska","position":{"start":{"line":8,"column":1},"end":{"line":8,"column":1}},"key":"hBVXHgFSyV"},{"type":"break","key":"ZvO9GyEzjg"},{"type":"text","value":"Tundra & Boreal Forest, Alaska","position":{"start":{"line":8,"column":1},"end":{"line":8,"column":1}},"key":"Q3anihrDTp"},{"type":"break","key":"bYCV1fnVU6"}],"key":"Z8wEkTDcG7"},{"type":"tableCell","position":{"start":{"line":8,"column":1},"end":{"line":8,"column":1}},"children":[{"type":"text","value":"March 7-17, 2022","position":{"start":{"line":8,"column":1},"end":{"line":8,"column":1}},"key":"u1xsreZgoB"},{"type":"break","key":"N9eOOagD72"},{"type":"text","value":"October 22-27, 2022","position":{"start":{"line":8,"column":1},"end":{"line":8,"column":1}},"key":"rE0V2Pxgow"},{"type":"break","key":"rXcEJcCouM"},{"type":"text","value":"March 7-16, 2023","position":{"start":{"line":8,"column":1},"end":{"line":8,"column":1}},"key":"eNK0TaQq1w"},{"type":"break","key":"heBDMon1Rb"},{"type":"text","value":"April 5-May 6, 2023","position":{"start":{"line":8,"column":1},"end":{"line":8,"column":1}},"key":"zgWDuLadVF"},{"type":"break","key":"Tx7SHdYgCt"},{"type":"text","value":"October 17-28, 2023","position":{"start":{"line":8,"column":1},"end":{"line":8,"column":1}},"key":"hB73o4QoDB"}],"key":"REH7ETfkxl"},{"type":"tableCell","align":"center","position":{"start":{"line":8,"column":1},"end":{"line":8,"column":1}},"children":[{"type":"text","value":"10,728","position":{"start":{"line":8,"column":1},"end":{"line":8,"column":1}},"key":"nIUktqfoXa"},{"type":"break","key":"ai2uR5e9sA"},{"type":"text","value":"9,049","position":{"start":{"line":8,"column":1},"end":{"line":8,"column":1}},"key":"vjGO8gGGp0"},{"type":"break","key":"jWvHrSPZyG"},{"type":"text","value":"26,750","position":{"start":{"line":8,"column":1},"end":{"line":8,"column":1}},"key":"dVqP03CFe1"},{"type":"break","key":"Qfdy2JulnQ"},{"type":"text","value":"TBD","position":{"start":{"line":8,"column":1},"end":{"line":8,"column":1}},"key":"aaIbjDbAbl"},{"type":"break","key":"IHQRHoY2pN"},{"type":"text","value":"6,350","position":{"start":{"line":8,"column":1},"end":{"line":8,"column":1}},"key":"vnwybrtg7o"}],"key":"WXG4HSiCjr"},{"type":"tableCell","align":"center","position":{"start":{"line":8,"column":1},"end":{"line":8,"column":1}},"children":[{"type":"text","value":"18","position":{"start":{"line":8,"column":1},"end":{"line":8,"column":1}},"key":"R8g921vq06"},{"type":"break","key":"GSlSvV4JmN"},{"type":"text","value":"186","position":{"start":{"line":8,"column":1},"end":{"line":8,"column":1}},"key":"nYB7BX0swd"},{"type":"break","key":"wKj4UqNOsv"},{"type":"text","value":"170","position":{"start":{"line":8,"column":1},"end":{"line":8,"column":1}},"key":"xSXSIK1gsu"},{"type":"break","key":"e1PDt4jXC4"},{"type":"text","value":"13","position":{"start":{"line":8,"column":1},"end":{"line":8,"column":1}},"key":"VWVsZQlaws"},{"type":"break","key":"FnBDgIY4TW"},{"type":"text","value":"127","position":{"start":{"line":8,"column":1},"end":{"line":8,"column":1}},"key":"iy741eiq4D"}],"key":"HLiOKaRDVx"}],"key":"BPSoRAWAsc"}],"key":"aNwimjUgY9"},{"type":"paragraph","position":{"start":{"line":10,"column":1},"end":{"line":10,"column":1}},"children":[{"type":"emphasis","position":{"start":{"line":10,"column":1},"end":{"line":10,"column":1}},"children":[{"type":"text","value":"*The majority of sites in 2020 have a temporal coverage of January-March due to the Covid-19 pandemic.","position":{"start":{"line":10,"column":1},"end":{"line":10,"column":1}},"key":"Gn8EEKjb8T"}],"key":"Oi4EiMuqaK"}],"key":"B1tDB6x4qw"}],"key":"jqraZkEnkZ"},{"type":"block","kind":"notebook-content","children":[{"type":"thematicBreak","position":{"start":{"line":1,"column":1},"end":{"line":1,"column":1}},"key":"NRCqO7T5Ie"},{"type":"heading","depth":3,"position":{"start":{"line":2,"column":1},"end":{"line":2,"column":1}},"children":[{"type":"text","value":"Snow Classification Coverage","position":{"start":{"line":2,"column":1},"end":{"line":2,"column":1}},"key":"tb4KTVkwvd"}],"identifier":"snow-classification-coverage","label":"Snow Classification Coverage","html_id":"snow-classification-coverage","implicit":true,"key":"RYZfSmfaND"},{"type":"comment","value":" Thanks to Sturm and Liston 2021 (and 1995), we have a global seasonal snow classification system. This is a vital mission planning tool for remote sensing snow studies. Revised from inception, the snow classification system offers improved utility of the climatological snow classes due to improved (much higher) resolution (300 m over North America). This data set can be found at NSIDC and downloaded at multiple resolutions.\n\n[NSIDC Global Seasonal-Snow Classification, Version 1](https://nsidc.org/data/NSIDC-0768/versions/1) \n\nCheck out [Sturm and Liston, 2021](https://journals.ametsoc.org/view/journals/hydr/22/11/JHM-D-21-0070.1.xml) to find out more \n    \n![](./content/01_snow-classes-sturm.png)\n**Figure 3.** Snow Classes across North America at 300 m (Sturm and Liston, 2021) ","key":"F0a82Thk9V"},{"type":"paragraph","position":{"start":{"line":13,"column":1},"end":{"line":13,"column":1}},"children":[{"type":"text","value":"As part of the mission statement, SnowEx aims to quantify snow estimation uncertainty across a range of snow classes, terrain and vegetation types. This is important to determine what areas and time periods have high SWE uncertainty across the ensemble of instrument techniques.","position":{"start":{"line":13,"column":1},"end":{"line":13,"column":1}},"key":"oRYi6Zilz4"}],"key":"rjn8xwuE5g"},{"type":"paragraph","position":{"start":{"line":16,"column":1},"end":{"line":17,"column":1}},"children":[{"type":"image","url":"/myst_assets_folder./content/01_map-n-barchart.png","position":{"start":{"line":16,"column":1},"end":{"line":16,"column":1}},"key":"iALdmJdULQ"},{"type":"text","value":"\n","position":{"start":{"line":16,"column":1},"end":{"line":16,"column":1}},"key":"vTuGet2cYr"},{"type":"strong","position":{"start":{"line":16,"column":1},"end":{"line":16,"column":1}},"children":[{"type":"text","value":"Figure 2.","position":{"start":{"line":16,"column":1},"end":{"line":16,"column":1}},"key":"z8Xi4rP2uh"}],"key":"oaUutkL90u"},{"type":"text","value":" Map of the in situ field visits for the duration of SnowEx field campaigns (2017-2023). At this scale, points are overlapping, especially in the eastern Rocky Mountain region around Colorado. The total number of unique visits with recorded SWE are listed in the legend. Upper Right Bar chart of snow classes over the four SnowEx field campaign years. Counts represent in situ field visits. A range of sites in Boreal and Montane Forests occurred in open areas such as meadows and clearings. The snow classification colors match those used in ","position":{"start":{"line":16,"column":1},"end":{"line":16,"column":1}},"key":"mdF66JrsdE"},{"type":"link","url":"https://journals.ametsoc.org/view/journals/hydr/22/11/JHM-D-21-0070.1.xml","position":{"start":{"line":16,"column":1},"end":{"line":16,"column":1}},"children":[{"type":"text","value":"Sturm and Liston, 2021","position":{"start":{"line":16,"column":1},"end":{"line":16,"column":1}},"key":"L2jcc4R9ow"}],"urlSource":"https://journals.ametsoc.org/view/journals/hydr/22/11/JHM-D-21-0070.1.xml","key":"u1CylCtWjg"},{"type":"text","value":".","position":{"start":{"line":16,"column":1},"end":{"line":16,"column":1}},"key":"CLgf6V5M5d"}],"key":"r0nCVBckVM"},{"type":"comment","value":" ![](./content/01_snow-classes-barchart.png)\n**Figure 2.** Bar chart of snow classes over the four SnowEx field campagin years. Counts represent in situ field visits. A range of sites in Boreal and Montane Forests occured in open areas such as meadows and clearings. The snow classification colors match those used in [Sturm and Liston, 2021](https://journals.ametsoc.org/view/journals/hydr/22/11/JHM-D-21-0070.1.xml).  ","key":"j4Aczp55eI"},{"type":"comment","value":" ![](./content/01_map-n-barchart.png)\n**Figure 2.** Bar chart of snow classes over the four SnowEx field campagin years. Counts represent in situ field visits. A range of sites in Boreal and Montane Forests occured in open areas such as meadows and clearings. The snow classification colors match those used in [Sturm and Liston, 2021](https://journals.ametsoc.org/view/journals/hydr/22/11/JHM-D-21-0070.1.xml). ","key":"jYNUI1ZYYo"}],"key":"gN1kwcAumu"},{"type":"block","kind":"notebook-content","children":[{"type":"heading","depth":3,"position":{"start":{"line":1,"column":1},"end":{"line":1,"column":1}},"children":[{"type":"text","value":"Recap","position":{"start":{"line":1,"column":1},"end":{"line":1,"column":1}},"key":"fBU2roRXAL"}],"identifier":"recap","label":"Recap","html_id":"recap","implicit":true,"key":"FhOBWoYMFi"},{"type":"list","ordered":false,"spread":false,"position":{"start":{"line":2,"column":1},"end":{"line":4,"column":1}},"children":[{"type":"listItem","spread":true,"position":{"start":{"line":2,"column":1},"end":{"line":3,"column":1}},"children":[{"type":"paragraph","position":{"start":{"line":2,"column":1},"end":{"line":2,"column":1}},"children":[{"type":"text","value":"SnowEx campaigns are structured based on the objectives set out in the SnowEx Science Plan. Some of those objectives are meet by conducting an all hands-on, short and intense observation period (IOP), while others are addressed by studying the evolution of the snowpack over a much longer time series (TS) style campaign.","position":{"start":{"line":2,"column":1},"end":{"line":2,"column":1}},"key":"zgG9winvHD"}],"key":"cMz5lUUZSJ"}],"key":"ebdn5WBZUV"},{"type":"listItem","spread":true,"position":{"start":{"line":4,"column":1},"end":{"line":4,"column":1}},"children":[{"type":"paragraph","position":{"start":{"line":4,"column":1},"end":{"line":4,"column":1}},"children":[{"type":"text","value":"The coincident field and airborne campaigns are designed to directly respond to the current knowledge gaps in remote sensing of seasonal snow, thus the participant-driven SnowEx effort targets a range of snow classes, terrain and vegetation types.","position":{"start":{"line":4,"column":1},"end":{"line":4,"column":1}},"key":"LXQCefwa24"}],"key":"pE9Bj30tI1"}],"key":"sUPjvFLHY7"}],"key":"raVUdjWIzs"}],"key":"OdocH7jUoy"},{"type":"block","kind":"notebook-content","children":[{"type":"heading","depth":3,"position":{"start":{"line":1,"column":1},"end":{"line":1,"column":1}},"children":[{"type":"text","value":"References","position":{"start":{"line":1,"column":1},"end":{"line":1,"column":1}},"key":"xCIP8YyW8A"}],"identifier":"references","label":"References","html_id":"references","implicit":true,"key":"OIe550Qbvy"},{"type":"paragraph","position":{"start":{"line":2,"column":1},"end":{"line":2,"column":1}},"children":[{"type":"text","value":"SnowEx Experimental Plans: 2017, ","position":{"start":{"line":2,"column":1},"end":{"line":2,"column":1}},"key":"oKx9ilmFkS"},{"type":"link","url":"https://snow.nasa.gov/sites/default/files/NASA_SnowEx_Experiment_Plan_v15_draft.pdf","position":{"start":{"line":2,"column":1},"end":{"line":2,"column":1}},"children":[{"type":"text","value":"2020","position":{"start":{"line":2,"column":1},"end":{"line":2,"column":1}},"key":"K623pF0PcK"}],"urlSource":"https://snow.nasa.gov/sites/default/files/NASA_SnowEx_Experiment_Plan_v15_draft.pdf","key":"eo0GXxKAU2"},{"type":"text","value":", ","position":{"start":{"line":2,"column":1},"end":{"line":2,"column":1}},"key":"DQNNcmJnbK"},{"type":"link","url":"https://snow.nasa.gov/sites/default/files/users/user354/SNEX-Campaigns/2021/NASASnowEx21_ExperimentPlan_draft_v02.pdf","position":{"start":{"line":2,"column":1},"end":{"line":2,"column":1}},"children":[{"type":"text","value":"2021","position":{"start":{"line":2,"column":1},"end":{"line":2,"column":1}},"key":"SHvZiJwRws"}],"urlSource":"https://snow.nasa.gov/sites/default/files/users/user354/SNEX-Campaigns/2021/NASASnowEx21_ExperimentPlan_draft_v02.pdf","key":"vt3E9sOt2V"},{"type":"text","value":", ","position":{"start":{"line":2,"column":1},"end":{"line":2,"column":1}},"key":"B4iDVXljmD"},{"type":"link","url":"https://snow.nasa.gov/sites/default/files/users/user354/SNEX-Campaigns/2023/NASA_SnowEx_Experiment_Plan_2023_draft_20June2024.pdf","position":{"start":{"line":2,"column":1},"end":{"line":2,"column":1}},"children":[{"type":"text","value":"2023","position":{"start":{"line":2,"column":1},"end":{"line":2,"column":1}},"key":"hdoN7psFsu"}],"urlSource":"https://snow.nasa.gov/sites/default/files/users/user354/SNEX-Campaigns/2023/NASA_SnowEx_Experiment_Plan_2023_draft_20June2024.pdf","key":"vC3DMm1e7X"}],"key":"P7DXhn3rKv"},{"type":"paragraph","position":{"start":{"line":4,"column":1},"end":{"line":4,"column":1}},"children":[{"type":"link","url":"https://snow.nasa.gov/sites/default/files/SnowEx_Science_Plan_v1.6.pdf","position":{"start":{"line":4,"column":1},"end":{"line":4,"column":1}},"children":[{"type":"text","value":"SnowEx Science Plan","position":{"start":{"line":4,"column":1},"end":{"line":4,"column":1}},"key":"brNZAAmEil"}],"urlSource":"https://snow.nasa.gov/sites/default/files/SnowEx_Science_Plan_v1.6.pdf","key":"obFK4ZdcRd"}],"key":"qsYB1BelSo"},{"type":"paragraph","position":{"start":{"line":6,"column":1},"end":{"line":6,"column":1}},"children":[{"type":"link","url":"https://journals.ametsoc.org/view/journals/hydr/22/11/JHM-D-21-0070.1.xml","position":{"start":{"line":6,"column":1},"end":{"line":6,"column":1}},"children":[{"type":"text","value":"Sturm and Liston, 2021","position":{"start":{"line":6,"column":1},"end":{"line":6,"column":1}},"key":"fgLa1hfkek"}],"urlSource":"https://journals.ametsoc.org/view/journals/hydr/22/11/JHM-D-21-0070.1.xml","key":"E5JmrZ6TdL"}],"key":"oI4HDsfOKc"}],"key":"spqnLXXTpC"}],"key":"EsEKCprziB"},"references":{"cite":{"order":[],"data":{}}},"footer":{"navigation":{"prev":{"title":"How to Cite This Cookbook","url":"/notebooks/how-to-cite","group":"Preamble"},"next":{"title":"Search and Download using earthaccess","url":"/notebooks/earthaccess-snowex","group":"Data Access"}}},"domain":"http://localhost:3000"}