{"version":2,"kind":"Notebook","sha256":"74a5bd979260a2365721ec5a8732e85190704c233921b84fd86e8a8dc2355786","slug":"notebooks.is2-snow-depth-workflow","location":"/notebooks/is2_snow_depth_workflow.ipynb","dependencies":[],"frontmatter":{"title":"Snow Depth Estimates with ICESat-2","content_includes_title":false,"kernelspec":{"name":"python3","display_name":"Python 3 (ipykernel)","language":"python"},"authors":[{"nameParsed":{"literal":"The SnowPit Community","given":"The SnowPit","family":"Community"},"name":"The SnowPit Community","id":"contributors-myst-generated-uid-0"}],"open_access":true,"license":{"content":{"id":"CC-BY-4.0","url":"https://creativecommons.org/licenses/by/4.0/","name":"Creative Commons Attribution 4.0 International","free":true,"CC":true},"code":{"id":"Apache-2.0","url":"https://opensource.org/licenses/Apache-2.0","name":"Apache License 2.0","free":true,"osi":true}},"github":"https://github.com/SnowEx/snow-cookbook","copyright":"2025","affiliations":[{"id":"UAlbany","name":"University at Albany (SUNY)","department":"Atmospheric and Environmental Sciences","url":"https://www.albany.edu/daes"},{"id":"CISL","name":"NSF National Center for Atmospheric Research","department":"Computational and Information Systems Lab","url":"https://www.cisl.ucar.edu"},{"id":"Unidata","name":"NSF Unidata","url":"https://www.unidata.ucar.edu"},{"id":"Argonne","name":"Argonne National Laboratory","department":"Environmental Science Division","url":"https://www.anl.gov/evs"},{"id":"CarbonPlan","name":"CarbonPlan","url":"https://carbonplan.org"},{"id":"NVIDIA","name":"NVIDIA Corporation","url":"https://www.nvidia.com/"}],"numbering":{"title":{"offset":1}},"source_url":"https://github.com/SnowEx/snow-cookbook/blob/HEAD/notebooks/is2_snow_depth_workflow.ipynb","edit_url":"https://github.com/SnowEx/snow-cookbook/edit/HEAD/notebooks/is2_snow_depth_workflow.ipynb","exports":[{"format":"ipynb","filename":"is2_snow_depth_workflow.ipynb","url":"/snow-cookbook/_preview/28/build/is2_snow_depth_workf-32a5c6a63385e7c3f2e1d3f58b7a3be9.ipynb"}]},"widgets":{},"mdast":{"type":"root","children":[{"type":"block","kind":"notebook-content","children":[{"type":"paragraph","position":{"start":{"line":3,"column":1},"end":{"line":3,"column":1}},"children":[{"type":"text","value":"This notebook uses a combination of ICESat-2 and airborne lidar to derive snow depth. It uses data from the SnowEx 2023 campaign as an example, but can be applied to other locations if a shapefile or geoJSON is given.","position":{"start":{"line":3,"column":1},"end":{"line":3,"column":1}},"key":"A1py2vZBcv"}],"key":"z9CVhBSso7"},{"type":"paragraph","position":{"start":{"line":5,"column":1},"end":{"line":5,"column":1}},"children":[{"type":"text","value":"This notebook is adapted from the 2023 ICESat-2 Hackweek, originally developed by Zachary Fair and Karina Zikan.","position":{"start":{"line":5,"column":1},"end":{"line":5,"column":1}},"key":"KLXxLqCydJ"}],"key":"PcZHnWTzem"}],"key":"eF7paHvhpn"},{"type":"block","kind":"notebook-content","children":[{"type":"heading","depth":2,"position":{"start":{"line":1,"column":1},"end":{"line":1,"column":1}},"children":[{"type":"text","value":"User input","position":{"start":{"line":1,"column":1},"end":{"line":1,"column":1}},"key":"gYskw1MNUL"}],"identifier":"user-input","label":"User input","html_id":"user-input","implicit":true,"key":"zEhHuYEwgg"},{"type":"paragraph","position":{"start":{"line":3,"column":1},"end":{"line":3,"column":1}},"children":[{"type":"text","value":"Acceptable field site IDs over Alaska are:","position":{"start":{"line":3,"column":1},"end":{"line":3,"column":1}},"key":"OzP7QN5kuK"}],"key":"dn3QlHxzWE"},{"type":"list","ordered":false,"spread":false,"position":{"start":{"line":4,"column":1},"end":{"line":9,"column":1}},"children":[{"type":"listItem","spread":true,"position":{"start":{"line":4,"column":1},"end":{"line":4,"column":1}},"children":[{"type":"paragraph","children":[{"type":"inlineCode","value":"cffl","position":{"start":{"line":4,"column":1},"end":{"line":4,"column":1}},"key":"yHUVZqVHmT"},{"type":"text","value":": Creamer’s Field/Farmer’s Loop","position":{"start":{"line":4,"column":1},"end":{"line":4,"column":1}},"key":"Gw6FqaH0Li"}],"key":"h8AFVBhrrl"}],"key":"W66M098gBQ"},{"type":"listItem","spread":true,"position":{"start":{"line":5,"column":1},"end":{"line":5,"column":1}},"children":[{"type":"paragraph","children":[{"type":"inlineCode","value":"cpcrw","position":{"start":{"line":5,"column":1},"end":{"line":5,"column":1}},"key":"e5Di9frw5P"},{"type":"text","value":": Caribou/Poker Creek Experimental Watershed","position":{"start":{"line":5,"column":1},"end":{"line":5,"column":1}},"key":"lObOhDaNEG"}],"key":"fEkgG5mb9V"}],"key":"y9aO1Fsc82"},{"type":"listItem","spread":true,"position":{"start":{"line":6,"column":1},"end":{"line":6,"column":1}},"children":[{"type":"paragraph","children":[{"type":"inlineCode","value":"bcef","position":{"start":{"line":6,"column":1},"end":{"line":6,"column":1}},"key":"sXBd36BayB"},{"type":"text","value":": Bonanza Creek Experimental Forest","position":{"start":{"line":6,"column":1},"end":{"line":6,"column":1}},"key":"KbrtDx3Bz9"}],"key":"HY7hUEAE2P"}],"key":"KsMiWWqXmL"},{"type":"listItem","spread":true,"position":{"start":{"line":7,"column":1},"end":{"line":7,"column":1}},"children":[{"type":"paragraph","children":[{"type":"inlineCode","value":"acp","position":{"start":{"line":7,"column":1},"end":{"line":7,"column":1}},"key":"y7BVIiPI4S"},{"type":"text","value":": Arctic Coastal Plain","position":{"start":{"line":7,"column":1},"end":{"line":7,"column":1}},"key":"MGVYSZkJOq"}],"key":"xwlcgM9vwj"}],"key":"iHsZa9kwi6"},{"type":"listItem","spread":true,"position":{"start":{"line":8,"column":1},"end":{"line":9,"column":1}},"children":[{"type":"paragraph","children":[{"type":"inlineCode","value":"utk","position":{"start":{"line":8,"column":1},"end":{"line":8,"column":1}},"key":"FzXPRmqIfG"},{"type":"text","value":": Toolik Research Station","position":{"start":{"line":8,"column":1},"end":{"line":8,"column":1}},"key":"neJwP21nNo"}],"key":"kbKM8uhwgb"}],"key":"cS2jJ7bitm"}],"key":"Kt3Mb8gLpS"},{"type":"paragraph","position":{"start":{"line":10,"column":1},"end":{"line":10,"column":1}},"children":[{"type":"text","value":"Acceptable IDs for Sliderule ATL08 class (use numeric ID):","position":{"start":{"line":10,"column":1},"end":{"line":10,"column":1}},"key":"kyJ7LbOlgQ"}],"key":"tAQBYdMvlR"},{"type":"list","ordered":false,"spread":false,"position":{"start":{"line":11,"column":1},"end":{"line":16,"column":1}},"children":[{"type":"listItem","spread":true,"position":{"start":{"line":11,"column":1},"end":{"line":11,"column":1}},"children":[{"type":"paragraph","children":[{"type":"inlineCode","value":"No classification:","position":{"start":{"line":11,"column":1},"end":{"line":11,"column":1}},"key":"CGhuUPZ5lK"},{"type":"text","value":" -1","position":{"start":{"line":11,"column":1},"end":{"line":11,"column":1}},"key":"AZoYoNLRAV"}],"key":"hAprJLitsK"}],"key":"mComigppsM"},{"type":"listItem","spread":true,"position":{"start":{"line":12,"column":1},"end":{"line":12,"column":1}},"children":[{"type":"paragraph","children":[{"type":"inlineCode","value":"atl08_unclassified","position":{"start":{"line":12,"column":1},"end":{"line":12,"column":1}},"key":"KTpfPmWrLE"},{"type":"text","value":": 0","position":{"start":{"line":12,"column":1},"end":{"line":12,"column":1}},"key":"gCjngl94MD"}],"key":"l8B4kFhRUQ"}],"key":"Zom0Bhxw83"},{"type":"listItem","spread":true,"position":{"start":{"line":13,"column":1},"end":{"line":13,"column":1}},"children":[{"type":"paragraph","children":[{"type":"inlineCode","value":"atl08_noise","position":{"start":{"line":13,"column":1},"end":{"line":13,"column":1}},"key":"B7wnXPeMCa"},{"type":"text","value":": 1","position":{"start":{"line":13,"column":1},"end":{"line":13,"column":1}},"key":"sK4Utq0SfN"}],"key":"IrlJChlsQq"}],"key":"T9Hjdb1ziJ"},{"type":"listItem","spread":true,"position":{"start":{"line":14,"column":1},"end":{"line":14,"column":1}},"children":[{"type":"paragraph","children":[{"type":"inlineCode","value":"atl08_canopy","position":{"start":{"line":14,"column":1},"end":{"line":14,"column":1}},"key":"AJty8pEoq9"},{"type":"text","value":": 2","position":{"start":{"line":14,"column":1},"end":{"line":14,"column":1}},"key":"GTq1MuZ7O0"}],"key":"veNaOPtKUf"}],"key":"o6G6zzzhZd"},{"type":"listItem","spread":true,"position":{"start":{"line":15,"column":1},"end":{"line":15,"column":1}},"children":[{"type":"paragraph","children":[{"type":"inlineCode","value":"atl08_top_of_canopy","position":{"start":{"line":15,"column":1},"end":{"line":15,"column":1}},"key":"F3z7wJdp7J"},{"type":"text","value":": 3","position":{"start":{"line":15,"column":1},"end":{"line":15,"column":1}},"key":"ZuKLW4dvS6"}],"key":"Qc4jCWu4Db"}],"key":"pf9dW27xeO"},{"type":"listItem","spread":true,"position":{"start":{"line":16,"column":1},"end":{"line":16,"column":1}},"children":[{"type":"paragraph","children":[{"type":"inlineCode","value":"atl08_ground","position":{"start":{"line":16,"column":1},"end":{"line":16,"column":1}},"key":"syt8EAZlVX"},{"type":"text","value":": 4","position":{"start":{"line":16,"column":1},"end":{"line":16,"column":1}},"key":"xSGEq6Ju4b"}],"key":"uVCrMqRuz8"}],"key":"wU9nDGJvcl"}],"key":"RabU4cAzCG"}],"key":"dnDFKDA356"},{"type":"block","kind":"notebook-code","children":[{"type":"code","lang":"python","executable":true,"value":"# Field site ID\nfield_id = 'C:/Users/zfair/OneDrive - NASA/Documents/Python/Projects/SnowPit/Workflows/cffl_lidar_box.geojson'\n\n# Snow-on (True) or snow-off (False) analysis\nsnow_on = True\n\n# Use March UAF data ('mar') or October depths ('oct')\nuaf_depths = 'mar'\n\n# Base data path\npath = '/home/jovyan/icesat2-snowex'\n\n# Desired RGT and date range for data queries. Set rgt to \"all\" if\n# all ground tracks are desired\ndate_range = ['2023-03-01', '2023-04-01']\nrgt = '1356'\n\n# SlideRule parameters (optional)\ncnf_surface = 4\natl08_class = 4\nsegment_length = 40\nres = 20","key":"c8PcGq7FWp"},{"type":"output","id":"fcTRrdM65WpAibrKP2gQV","data":[],"key":"Y5RCvxm4zE"}],"key":"IMrXxOfQkY"},{"type":"block","kind":"notebook-content","children":[{"type":"paragraph","position":{"start":{"line":1,"column":1},"end":{"line":1,"column":1}},"children":[{"type":"text","value":"A breakdown of the SlideRule parameters above:","position":{"start":{"line":1,"column":1},"end":{"line":1,"column":1}},"key":"xUwnLe7a1D"}],"key":"Ye1RmFVm54"},{"type":"paragraph","position":{"start":{"line":3,"column":1},"end":{"line":3,"column":1}},"children":[{"type":"inlineCode","value":"cnf_surface","position":{"start":{"line":3,"column":1},"end":{"line":3,"column":1}},"key":"m948kCyTTA"},{"type":"text","value":": The confidence level of the ICESat-2 photons.","position":{"start":{"line":3,"column":1},"end":{"line":3,"column":1}},"key":"jq6hbhjyGX"}],"key":"Uffr2YJ74l"},{"type":"list","ordered":false,"spread":false,"position":{"start":{"line":4,"column":1},"end":{"line":9,"column":1}},"children":[{"type":"listItem","spread":true,"position":{"start":{"line":4,"column":1},"end":{"line":4,"column":1}},"children":[{"type":"paragraph","children":[{"type":"text","value":"High-confidence photons (recommended for snow): 4","position":{"start":{"line":4,"column":1},"end":{"line":4,"column":1}},"key":"JI3htbZcxE"}],"key":"nj5RxwReEV"}],"key":"bqBKaZeMvt"},{"type":"listItem","spread":true,"position":{"start":{"line":5,"column":1},"end":{"line":5,"column":1}},"children":[{"type":"paragraph","children":[{"type":"text","value":"High-/medium-confidence photons: 3","position":{"start":{"line":5,"column":1},"end":{"line":5,"column":1}},"key":"iprDWe6CPL"}],"key":"qXrKBq184J"}],"key":"iSqbtIKoyJ"},{"type":"listItem","spread":true,"position":{"start":{"line":6,"column":1},"end":{"line":6,"column":1}},"children":[{"type":"paragraph","children":[{"type":"text","value":"High-/medium-/low-confidence photons: 2","position":{"start":{"line":6,"column":1},"end":{"line":6,"column":1}},"key":"SKCL0hgrv7"}],"key":"L6ssB6BoRc"}],"key":"EPmU92XeRX"},{"type":"listItem","spread":true,"position":{"start":{"line":7,"column":1},"end":{"line":7,"column":1}},"children":[{"type":"paragraph","children":[{"type":"text","value":"Signal photons (high/medium/low) and noise: 1","position":{"start":{"line":7,"column":1},"end":{"line":7,"column":1}},"key":"GNB1VfERfs"}],"key":"LQrDU96syI"}],"key":"rYhgQ8zSuZ"},{"type":"listItem","spread":true,"position":{"start":{"line":8,"column":1},"end":{"line":9,"column":1}},"children":[{"type":"paragraph","children":[{"type":"text","value":"Signal photons, noise, and solar background (not recommended): 0","position":{"start":{"line":8,"column":1},"end":{"line":8,"column":1}},"key":"DH3BZAEp3C"}],"key":"XHtzAx0j33"}],"key":"NaOY1B2UjF"}],"key":"Gk8yBsKY5X"},{"type":"paragraph","position":{"start":{"line":10,"column":1},"end":{"line":10,"column":1}},"children":[{"type":"inlineCode","value":"segment_length","position":{"start":{"line":10,"column":1},"end":{"line":10,"column":1}},"key":"UeTvIAl0UW"},{"type":"text","value":": The along-track length to sample and aggregate photons, in meters. Currently set at 40 m, the resolution of the ATL06 product.","position":{"start":{"line":10,"column":1},"end":{"line":10,"column":1}},"key":"DsFr9Y2t0J"}],"key":"oef5xNfNM4"},{"type":"paragraph","position":{"start":{"line":12,"column":1},"end":{"line":12,"column":1}},"children":[{"type":"inlineCode","value":"res","position":{"start":{"line":12,"column":1},"end":{"line":12,"column":1}},"key":"OUkXWxzJt0"},{"type":"text","value":": The along-track resolution of the returned data product. Currently set at 20 m to match ATL06.","position":{"start":{"line":12,"column":1},"end":{"line":12,"column":1}},"key":"ggECMSuOtW"}],"key":"VGZzm8hHan"}],"key":"ehxkyMOxZj"},{"type":"block","kind":"notebook-content","children":[{"type":"heading","depth":2,"position":{"start":{"line":1,"column":1},"end":{"line":1,"column":1}},"children":[{"type":"text","value":"Read ICESat-2 data","position":{"start":{"line":1,"column":1},"end":{"line":1,"column":1}},"key":"aj0WqArZ5x"}],"identifier":"read-icesat-2-data","label":"Read ICESat-2 data","html_id":"read-icesat-2-data","implicit":true,"key":"fYoXeA0tKp"},{"type":"paragraph","position":{"start":{"line":2,"column":1},"end":{"line":2,"column":1}},"children":[{"type":"text","value":"To load the ICESat-2 data with minimal effort from the user, we will use SlideRule in the below function.","position":{"start":{"line":2,"column":1},"end":{"line":2,"column":1}},"key":"R2UaimmSaY"}],"key":"M9DduP9xqu"}],"key":"l3Mc8dbrtJ"},{"type":"block","kind":"notebook-code","children":[{"type":"code","lang":"python","executable":true,"value":"from sliderule import sliderule, icesat2\n\ndef atl06srq(field_geojson, date_range, rgt, cnf_surface, atl08_class, \n             segment_length, res):\n    # Initiate SlideRule\n    icesat2.init('slideruleearth.io', verbose=False)\n\n    # Load geoJSON for site of interest\n    region = sliderule.toregion(field_geojson)['poly']\n\n    # Convert user-defined ATL08 class ID to string readable by SlideRule\n    atl08_ids = {-1: 'None',\n                 0: 'atl08_unclassified',\n                 1: 'atl08_noise',\n                 2: 'atl08_canopy',\n                 3: 'atl08_top_of_canopy',\n                 4: 'atl08_ground'}\n\n    # Construct dictionary of parameters\n    time_root = 'T00:00:00Z'\n    parms = {\n             \"poly\": region,\n             \"srt\": icesat2.SRT_LAND,\n             \"cnf\": cnf_surface,\n             \"len\": segment_length,\n             \"res\": res,\n             \"t0\": date_range[0]+time_root,\n             \"t1\": date_range[1]+time_root\n            }\n\n    # Check if all RGTs are considered, or only a subset\n    if rgt != \"all\":\n        parms[\"rgt\"] = rgt\n        print(f\"Subsetting to only include ICESat-2 RGT {rgt}.\")\n\n    # Check for ATL08 filter\n    if atl08_ids.get(atl08_class) != \"None\":\n        parms[\"atl08_class\"] = atl08_ids.get(atl08_class)\n        print(\"Subsetting by selected ATL08 filter...\")\n\n    # Query SlideRule\n    atl06sr = icesat2.atl06p(parms)\n\n    return atl06sr","key":"DrQ5mwhTVf"},{"type":"output","id":"uk9mfNg1nWTg98RzqoMSx","data":[{"output_type":"error","traceback":"\u001b[31m---------------------------------------------------------------------------\u001b[39m\n\u001b[31mModuleNotFoundError\u001b[39m                       Traceback (most recent call last)\n\u001b[36mCell\u001b[39m\u001b[36m \u001b[39m\u001b[32mIn[2]\u001b[39m\u001b[32m, line 1\u001b[39m\n\u001b[32m----> \u001b[39m\u001b[32m1\u001b[39m \u001b[38;5;28;01mfrom\u001b[39;00m\u001b[38;5;250m \u001b[39m\u001b[34;01msliderule\u001b[39;00m\u001b[38;5;250m \u001b[39m\u001b[38;5;28;01mimport\u001b[39;00m sliderule, icesat2\n\u001b[32m      3\u001b[39m \u001b[38;5;28;01mdef\u001b[39;00m\u001b[38;5;250m \u001b[39m\u001b[34matl06srq\u001b[39m(field_geojson, date_range, rgt, cnf_surface, atl08_class, \n\u001b[32m      4\u001b[39m              segment_length, res):\n\u001b[32m      5\u001b[39m     \u001b[38;5;66;03m# Initiate SlideRule\u001b[39;00m\n\u001b[32m      6\u001b[39m     icesat2.init(\u001b[33m'\u001b[39m\u001b[33mslideruleearth.io\u001b[39m\u001b[33m'\u001b[39m, verbose=\u001b[38;5;28;01mFalse\u001b[39;00m)\n\n\u001b[31mModuleNotFoundError\u001b[39m: No module named 'sliderule'","ename":"ModuleNotFoundError","evalue":"No module named 'sliderule'"}],"key":"Qv55IYqvjS"}],"key":"L8yRpID6h3"},{"type":"block","kind":"notebook-code","children":[{"type":"code","lang":"python","executable":true,"value":"# Generate ICESat-2 data from SlideRule\natl06sr = atl06srq(field_id, date_range, rgt,\n                 cnf_surface=cnf_surface,\n                 atl08_class=atl08_class,\n                 segment_length=segment_length,\n                 res=res)","key":"aBXNbu3uSo"},{"type":"output","id":"p8FY34gyOb2H9FWHcZ_pb","data":[],"key":"h4k8pY6ZEH"}],"key":"XboD0agpEJ"},{"type":"block","kind":"notebook-code","children":[{"type":"code","lang":"python","executable":true,"value":"# Convert ATL06SR to geodataframe in EPSG:32606\natl06sr['lon'], atl06sr['lat'] = atl06sr.geometry.x, atl06sr.geometry.y\natl06sr_gdf = atl06sr.to_crs('epsg:32606')","key":"f4NG5qOVVZ"},{"type":"output","id":"z77rg4LKOxkuPC5CLFIO8","data":[],"key":"HMzNiBKRFu"}],"key":"QBfMq20D0C"},{"type":"block","kind":"notebook-code","data":{"scrolled":true},"children":[{"type":"code","lang":"python","executable":true,"value":"atl06sr","key":"iLHtHeGFxR"},{"type":"output","id":"_6jWa0c2TKMA_s93mZtIi","data":[],"key":"MSU6jz4tEM"}],"key":"XfgZF4jXs8"},{"type":"block","kind":"notebook-content","children":[{"type":"heading","depth":2,"position":{"start":{"line":1,"column":1},"end":{"line":1,"column":1}},"children":[{"type":"text","value":"Read Airborne Lidar Data","position":{"start":{"line":1,"column":1},"end":{"line":1,"column":1}},"key":"o8RhmlTmdn"}],"identifier":"read-airborne-lidar-data","label":"Read Airborne Lidar Data","html_id":"read-airborne-lidar-data","implicit":true,"key":"eMduUv6on6"},{"type":"paragraph","position":{"start":{"line":3,"column":1},"end":{"line":3,"column":1}},"children":[{"type":"text","value":"To derive snow depth with ICESat-2, we need a snow-off digital elevation model (DEM), which commonly originates from airborne lidar. This next step is designed to load and prepare some airborne lidar data from the University of Alaska, Fairbanks for this analysis.","position":{"start":{"line":3,"column":1},"end":{"line":3,"column":1}},"key":"sokdlk9qtD"}],"key":"sMceO8ECfx"},{"type":"paragraph","position":{"start":{"line":5,"column":1},"end":{"line":5,"column":1}},"children":[{"type":"text","value":"The method currently presented uses ","position":{"start":{"line":5,"column":1},"end":{"line":5,"column":1}},"key":"ZFQ0zVqrlZ"},{"type":"inlineCode","value":"earthaccess","position":{"start":{"line":5,"column":1},"end":{"line":5,"column":1}},"key":"ToYs4CDPtM"},{"type":"text","value":" to stream the data without any download required. However, this process can be slow on a local machine, and may be memory-intensive on a cloud environment. A more streamlined workflow utilizing the SnowEx Database is in the works, though the given method is most effective for non-SnowEx DEM sources.","position":{"start":{"line":5,"column":1},"end":{"line":5,"column":1}},"key":"VPW2CvZ6p0"}],"key":"AQ0M8GeJsM"}],"key":"DUjipWqg8V"},{"type":"block","kind":"notebook-code","children":[{"type":"code","lang":"python","executable":true,"value":"import earthaccess\nimport xarray as xr\nearthaccess.login(strategy='interactive', persist=True)\nauth = earthaccess.login()","key":"aHukLnbnxf"},{"type":"output","id":"G0WhDN-GaMMsf1QcezNsV","data":[],"key":"NrkCwQN9Ar"}],"key":"sgG4KwzExJ"},{"type":"block","kind":"notebook-code","children":[{"type":"code","lang":"python","executable":true,"value":"region = sliderule.toregion(field_id)['poly']\ncoords = [(point[\"lon\"], point[\"lat\"]) for point in region]","key":"DIRZPNAdct"},{"type":"output","id":"1fN3vTjNAD7jB86Xn1KZ-","data":[],"key":"okUV6U3DdZ"}],"key":"Z5OAnPHXwx"},{"type":"block","kind":"notebook-code","children":[{"type":"code","lang":"python","executable":true,"value":"# Coordinates for SW/NE corners\nlon_min = min([coord[0] for coord in coords])\nlat_min = min([coord[1] for coord in coords])\nlon_max = max([coord[0] for coord in coords])\nlat_max = max([coord[1] for coord in coords])\n\n# Data query for lidar snow depth over Fairbanks, AK\nresults = earthaccess.search_data(\n    short_name='SNEX23_Lidar',\n    bounding_box = (lon_min, lat_min, lon_max, lat_max),\n    temporal = ('2023-03-10', '2023-03-15')\n)\n\nfiles = earthaccess.open(results)\nlidar_snow_on = xr.open_dataset(files[1], engine='rasterio')","key":"l41NLS8ZUC"},{"type":"output","id":"1YtA-RSCdQvkRxmlhR3qo","data":[],"key":"AffRPWiv9K"}],"key":"Y7z8Yh7UXe"},{"type":"block","kind":"notebook-code","children":[{"type":"code","lang":"python","executable":true,"value":"lidar_snow_on","key":"R8Ypn7Erpd"},{"type":"output","id":"HTaM3bgbP3Y_m-ZrNuJFZ","data":[],"key":"y530FntkL9"}],"key":"jYn2ajYyUx"},{"type":"block","kind":"notebook-code","children":[{"type":"code","lang":"python","executable":true,"value":"# Data query for lidar snow-off elevation over Fairbanks, AK\nresults = earthaccess.search_data(\n    short_name='SNEX23_Lidar',\n    bounding_box = (lon_min, lat_min, lon_max, lat_max),\n    temporal = ('2022-05-20', '2022-05-31')\n)\n\n# Open the resulting GeoTiff into Xarray\nfiles = earthaccess.open(results)\nlidar_snow_off = xr.open_dataset(files[1], engine='rasterio')","key":"KQdvDiZ4Y7"},{"type":"output","id":"HSAhwWdGn98pTuNzYtoph","data":[],"key":"nArgL4shQc"}],"key":"PtA1YqXq3I"},{"type":"block","kind":"notebook-content","children":[{"type":"heading","depth":2,"position":{"start":{"line":1,"column":1},"end":{"line":1,"column":1}},"children":[{"type":"text","value":"Co-Locate ICESat-2 and UAF Lidar","position":{"start":{"line":1,"column":1},"end":{"line":1,"column":1}},"key":"pKcROndIHi"}],"identifier":"co-locate-icesat-2-and-uaf-lidar","label":"Co-Locate ICESat-2 and UAF Lidar","html_id":"co-locate-icesat-2-and-uaf-lidar","implicit":true,"key":"Dvdrf1YfZ3"},{"type":"paragraph","position":{"start":{"line":3,"column":1},"end":{"line":3,"column":1}},"children":[{"type":"text","value":"For this step, we will co-locate ICESat-2 and UAF so that we can directly compare the two datasets. The co-location will use a statistical method called “spline interpolation”, and we will perform this co-location with both the snow-on and snow-off data.","position":{"start":{"line":3,"column":1},"end":{"line":3,"column":1}},"key":"BuDEy3VVYX"}],"key":"GvCJwOZFyV"},{"type":"paragraph","position":{"start":{"line":5,"column":1},"end":{"line":5,"column":1}},"children":[{"type":"text","value":"The below function has the code needed to perform the co-location.","position":{"start":{"line":5,"column":1},"end":{"line":5,"column":1}},"key":"OH07Sq11Up"}],"key":"x3EyL4WKJO"}],"key":"XK3vKH8oWx"},{"type":"block","kind":"notebook-code","children":[{"type":"code","lang":"python","executable":true,"value":"# Packages needed for the below functions\nimport geopandas as gpd\nimport numpy as np\nimport pandas as pd\nfrom scipy.interpolate import RectBivariateSpline\n\ndef colocate_is2(lidar_snow_off, lidar_snow_on, is2_data):\n    # Ensure lidar/ICESat-2 projections match\n    if is2_data.crs!=32606:\n        is2_data.to_crs(\"EPSG:32606\", inplace=True)\n    \n    # Define x/y coordinates from snow-off data\n    x0, y0 = np.array(lidar_snow_off.x), np.array(lidar_snow_off.y)\n\n    # Do the same, but for the snow depth data\n    xs, ys = np.array(lidar_snow_on.x), np.array(lidar_snow_on.y)\n\n    # Remove filler values that would mess up the interpolator\n    dem_heights = np.array(lidar_snow_off['band_data'].sel(band=1))[::-1,:]\n    dem_heights[np.isnan(dem_heights)] = -9999\n    dem_depths = np.array(lidar_snow_on['band_data'].sel(band=1))[::-1,:]\n    dem_depths[np.isnan(dem_depths)] = -9999\n\n    # Generate interpolator schemes\n    interp_height = RectBivariateSpline(np.array(y0)[::-1], \n                                        np.array(x0),\n                                        dem_heights)\n    interp_depth = RectBivariateSpline(np.array(ys)[::-1],\n                                       np.array(xs),\n                                       dem_depths)\n\n    # Use the spline interpolator to align the lidar with ICESat-2\n    is2_lidar_df = pd.DataFrame()\n    for beam in np.unique(is2_data['gt']):\n        # Subset ICESat-2 data by current beam\n        is2_tmp = is2_data.loc[is2_data['gt']==beam]\n\n        # ICESat-2 x/y coordinates\n        xn, yn = is2_tmp.geometry.x, is2_tmp.geometry.y\n\n        # Define indices within x/y bounds of DEM\n        i1 = (xn>np.min(x0)) & (xn<np.max(x0))\n        i1 &= (yn>np.min(y0)) & (yn<np.max(y0))\n\n        # Estimate lidar elevation and snow depth along ICESat-2 track\n        lidar_height = interp_height(yn[i1], xn[i1], grid=False)\n        lidar_depth = interp_depth(yn[i1], xn[i1], grid=False)\n\n        # Construct dataframe of ICESat-2 and lidar data\n        tmp = pd.DataFrame(data={'lat': is2_tmp['lat'][i1],\n                                 'lon': is2_tmp['lon'][i1],\n                                 'x': xn[i1],\n                                 'y': yn[i1],\n                                 'rgt': is2_tmp['rgt'][i1],\n                                 'beam': is2_tmp['gt'][i1],\n                                 'is2_height': is2_tmp['h_mean'][i1],\n                                 'n_fit_photons': is2_tmp['n_fit_photons'][i1],\n                                 'h_sigma': is2_tmp['h_sigma'][i1],\n                                 'dh_fit_dx': is2_tmp['dh_fit_dx'][i1],\n                                 'lidar_height': lidar_height,\n                                 'lidar_snow_depth': lidar_depth\n                                    }\n                              )\n        # Concatenate the co-located data into  final DataFrame\n        is2_lidar_df = pd.concat([is2_lidar_df, tmp])\n\n    return is2_lidar_df","key":"JW9JP49N0e"},{"type":"output","id":"2rQ6TTN4zQqHi4PIAcFlU","data":[],"key":"QI8GTAVRFo"}],"key":"SD0m3ijXJL"},{"type":"block","kind":"notebook-code","children":[{"type":"code","lang":"python","executable":true,"value":"# Use the above function to co-locate the airborne lidar and ICESat-2\natl06sr_uaf = colocate_is2(lidar_snow_off, lidar_snow_on, atl06sr)\n\n# Estimate the ICESat-2 snow depth\natl06sr_uaf['is2_snow_depth'] = atl06sr_uaf['is2_height'] - atl06sr_uaf['lidar_height']\n\n# Convert final DataFrame in GeoDataFrame\natl06sr_uaf_gdf = gpd.GeoDataFrame(atl06sr_uaf,\n                                   geometry=gpd.points_from_xy(atl06sr_uaf.lon, atl06sr_uaf.lat),\n                                   crs='EPSG:4326')\n\natl06sr_uaf_gdf","key":"J1F4TYkbWj"},{"type":"output","id":"TntdOi4iwYGPG9aRpDjoV","data":[],"key":"hUHFLcifQq"}],"key":"wdeyaDEsWk"},{"type":"block","kind":"notebook-content","children":[{"type":"paragraph","position":{"start":{"line":1,"column":1},"end":{"line":1,"column":1}},"children":[{"type":"text","value":"An outline of the variables in our current GeoDataFrame:","position":{"start":{"line":1,"column":1},"end":{"line":1,"column":1}},"key":"ixgP7c5ess"}],"key":"G59bRDhk7Z"},{"type":"list","ordered":false,"spread":false,"position":{"start":{"line":2,"column":1},"end":{"line":12,"column":1}},"children":[{"type":"listItem","spread":true,"position":{"start":{"line":2,"column":1},"end":{"line":2,"column":1}},"children":[{"type":"paragraph","children":[{"type":"inlineCode","value":"lat","position":{"start":{"line":2,"column":1},"end":{"line":2,"column":1}},"key":"rY48V1XGuT"},{"type":"text","value":" and ","position":{"start":{"line":2,"column":1},"end":{"line":2,"column":1}},"key":"ilPsEqBv53"},{"type":"inlineCode","value":"lon","position":{"start":{"line":2,"column":1},"end":{"line":2,"column":1}},"key":"Q93XKx6e4s"},{"type":"text","value":": The latitude and longitude along the ICESat-2 track.","position":{"start":{"line":2,"column":1},"end":{"line":2,"column":1}},"key":"rUaxXaKl5k"}],"key":"HcZdj57Rxz"}],"key":"eO7q6T281J"},{"type":"listItem","spread":true,"position":{"start":{"line":3,"column":1},"end":{"line":3,"column":1}},"children":[{"type":"paragraph","children":[{"type":"inlineCode","value":"x","position":{"start":{"line":3,"column":1},"end":{"line":3,"column":1}},"key":"QaXHnAhKT9"},{"type":"text","value":" and ","position":{"start":{"line":3,"column":1},"end":{"line":3,"column":1}},"key":"v1IAQIEK9o"},{"type":"inlineCode","value":"y","position":{"start":{"line":3,"column":1},"end":{"line":3,"column":1}},"key":"dcrJeZSRwD"},{"type":"text","value":": The easting and northing along the ICESat-2 track, in projection EPSG:32606.","position":{"start":{"line":3,"column":1},"end":{"line":3,"column":1}},"key":"nNNTgqcw7P"}],"key":"jFXrIBzNdM"}],"key":"zGav46Lb8E"},{"type":"listItem","spread":true,"position":{"start":{"line":4,"column":1},"end":{"line":4,"column":1}},"children":[{"type":"paragraph","children":[{"type":"inlineCode","value":"rgt","position":{"start":{"line":4,"column":1},"end":{"line":4,"column":1}},"key":"o2nsxszXWC"},{"type":"text","value":": The reference ground track number of the ICESat-2 track of interest.","position":{"start":{"line":4,"column":1},"end":{"line":4,"column":1}},"key":"yu9ibLyaxo"}],"key":"hrnxO7K5R2"}],"key":"A5v5hkrT84"},{"type":"listItem","spread":true,"position":{"start":{"line":5,"column":1},"end":{"line":5,"column":1}},"children":[{"type":"paragraph","children":[{"type":"inlineCode","value":"beam","position":{"start":{"line":5,"column":1},"end":{"line":5,"column":1}},"key":"XfpkpYIfTn"},{"type":"text","value":": The ICESat-2 beam designation (gt1l, gt2r, etc.)","position":{"start":{"line":5,"column":1},"end":{"line":5,"column":1}},"key":"TTldignXLv"}],"key":"XWf7QeIzHT"}],"key":"z85q4Z4CSg"},{"type":"listItem","spread":true,"position":{"start":{"line":6,"column":1},"end":{"line":6,"column":1}},"children":[{"type":"paragraph","children":[{"type":"inlineCode","value":"is2_height","position":{"start":{"line":6,"column":1},"end":{"line":6,"column":1}},"key":"QtKlWSEqME"},{"type":"text","value":": ICESat-2 height estimate at the given location.","position":{"start":{"line":6,"column":1},"end":{"line":6,"column":1}},"key":"Kg8n1VDzX0"}],"key":"i8t4o1E1NM"}],"key":"R5AKV4I1ji"},{"type":"listItem","spread":true,"position":{"start":{"line":7,"column":1},"end":{"line":7,"column":1}},"children":[{"type":"paragraph","children":[{"type":"inlineCode","value":"n_fit_photons","position":{"start":{"line":7,"column":1},"end":{"line":7,"column":1}},"key":"gi2zzs8EyI"},{"type":"text","value":": Number of ICESat-2 photons used to derive ","position":{"start":{"line":7,"column":1},"end":{"line":7,"column":1}},"key":"j0fvHwPnmf"},{"type":"inlineCode","value":"is2_height","position":{"start":{"line":7,"column":1},"end":{"line":7,"column":1}},"key":"zz0A4zC47V"},{"type":"text","value":".","position":{"start":{"line":7,"column":1},"end":{"line":7,"column":1}},"key":"paEuEiKDyt"}],"key":"gMoJTsEIx6"}],"key":"vd0xEzvr7o"},{"type":"listItem","spread":true,"position":{"start":{"line":8,"column":1},"end":{"line":8,"column":1}},"children":[{"type":"paragraph","children":[{"type":"inlineCode","value":"h_sigma","position":{"start":{"line":8,"column":1},"end":{"line":8,"column":1}},"key":"dr1STgGIcp"},{"type":"text","value":": Approximate uncertainty of ","position":{"start":{"line":8,"column":1},"end":{"line":8,"column":1}},"key":"qkxq2in6K4"},{"type":"inlineCode","value":"is2_height","position":{"start":{"line":8,"column":1},"end":{"line":8,"column":1}},"key":"i9They3rM9"},{"type":"text","value":".","position":{"start":{"line":8,"column":1},"end":{"line":8,"column":1}},"key":"y8nW7926fo"}],"key":"tyJiKYZGnu"}],"key":"JW6s9XZXkG"},{"type":"listItem","spread":true,"position":{"start":{"line":9,"column":1},"end":{"line":9,"column":1}},"children":[{"type":"paragraph","children":[{"type":"inlineCode","value":"dh_fit_dx","position":{"start":{"line":9,"column":1},"end":{"line":9,"column":1}},"key":"Uvtgg7efBe"},{"type":"text","value":": A rough measure of surface slope along the ICESat-2 track.","position":{"start":{"line":9,"column":1},"end":{"line":9,"column":1}},"key":"InrkKb44Lp"}],"key":"RC6dTwEGb0"}],"key":"HLVUzOjHz3"},{"type":"listItem","spread":true,"position":{"start":{"line":10,"column":1},"end":{"line":10,"column":1}},"children":[{"type":"paragraph","children":[{"type":"inlineCode","value":"lidar_height","position":{"start":{"line":10,"column":1},"end":{"line":10,"column":1}},"key":"Bo6jgqkTSu"},{"type":"text","value":": Lidar height estimate at the given location.","position":{"start":{"line":10,"column":1},"end":{"line":10,"column":1}},"key":"YK31eqYNyH"}],"key":"qw3PyJ8Kno"}],"key":"RdlvOCSWen"},{"type":"listItem","spread":true,"position":{"start":{"line":11,"column":1},"end":{"line":11,"column":1}},"children":[{"type":"paragraph","children":[{"type":"inlineCode","value":"lidar_snow_depth","position":{"start":{"line":11,"column":1},"end":{"line":11,"column":1}},"key":"tIjTYhwaxp"},{"type":"text","value":": Lidar snow depth estimate at the given location.","position":{"start":{"line":11,"column":1},"end":{"line":11,"column":1}},"key":"hRBDbAKC58"}],"key":"WLKtoIJKvQ"}],"key":"NPwMDuOG2o"},{"type":"listItem","spread":true,"position":{"start":{"line":12,"column":1},"end":{"line":12,"column":1}},"children":[{"type":"paragraph","children":[{"type":"inlineCode","value":"is2_snow_depth","position":{"start":{"line":12,"column":1},"end":{"line":12,"column":1}},"key":"fcUVUKhJOX"},{"type":"text","value":": ICESat-2 snow depth estimate at the given location.","position":{"start":{"line":12,"column":1},"end":{"line":12,"column":1}},"key":"E6pRkAft2J"}],"key":"aZzJKHz7rl"}],"key":"HAAPucmWVD"}],"key":"TQqoCr2ZLT"}],"key":"rvOwo3NCQn"},{"type":"block","kind":"notebook-content","children":[{"type":"paragraph","position":{"start":{"line":1,"column":1},"end":{"line":1,"column":1}},"children":[{"type":"text","value":"The key variables are ","position":{"start":{"line":1,"column":1},"end":{"line":1,"column":1}},"key":"BWnMDrHN94"},{"type":"inlineCode","value":"is2_snow_depth","position":{"start":{"line":1,"column":1},"end":{"line":1,"column":1}},"key":"iS9Fasnlro"},{"type":"text","value":" and ","position":{"start":{"line":1,"column":1},"end":{"line":1,"column":1}},"key":"WmMs7PwaQd"},{"type":"inlineCode","value":"lidar_snow_depth","position":{"start":{"line":1,"column":1},"end":{"line":1,"column":1}},"key":"BD2cbW7WNg"},{"type":"text","value":" for our comparisons. Several of the other variables, such as ","position":{"start":{"line":1,"column":1},"end":{"line":1,"column":1}},"key":"us8573Jpvj"},{"type":"inlineCode","value":"n_fit_photons","position":{"start":{"line":1,"column":1},"end":{"line":1,"column":1}},"key":"cDquYm9Fu2"},{"type":"text","value":" and ","position":{"start":{"line":1,"column":1},"end":{"line":1,"column":1}},"key":"oScPn7rjrr"},{"type":"inlineCode","value":"h_sigma","position":{"start":{"line":1,"column":1},"end":{"line":1,"column":1}},"key":"W2iXaiLvE1"},{"type":"text","value":", can be used to filter or process the data further, if desired.","position":{"start":{"line":1,"column":1},"end":{"line":1,"column":1}},"key":"mrcQcF2D7y"}],"key":"QlieY7BMr0"},{"type":"paragraph","position":{"start":{"line":3,"column":1},"end":{"line":3,"column":1}},"children":[{"type":"text","value":"Let’s look at a simple comparison between the two depth products.","position":{"start":{"line":3,"column":1},"end":{"line":3,"column":1}},"key":"WvfUaGAcVe"}],"key":"CCTNIrQZkt"}],"key":"MQ8PUM3Tnw"},{"type":"block","kind":"notebook-code","children":[{"type":"code","lang":"python","executable":true,"value":"# Remove sub-zero values\natl06sr_uaf_gdf = atl06sr_uaf_gdf[atl06sr_uaf_gdf['is2_snow_depth']>=0]\natl06sr_uaf_gdf = atl06sr_uaf_gdf[atl06sr_uaf_gdf['lidar_snow_depth']>=0]","key":"MKgIrS5z8K"},{"type":"output","id":"8cXOF62kBVm2G9xwkLfg8","data":[],"key":"JbbEFpJ1sR"}],"key":"Nbj84jZ31F"},{"type":"block","kind":"notebook-code","children":[{"type":"code","lang":"python","executable":true,"value":"import matplotlib.pyplot as plt\n\nsingle_beam = atl06sr_uaf_gdf[atl06sr_uaf_gdf['beam']==60]\n\n# Line plot of along-track snow depths\nfig, ax = plt.subplots(figsize=(9,6))\nsingle_beam.plot(kind='line', ax=ax, x='lat', y='is2_snow_depth',\n                     linewidth=3, label='ICESat-2')\nsingle_beam.plot(kind='line', ax=ax, x='lat', y='lidar_snow_depth',\n                     linewidth=1.5, color='orange', label='UAF lidar')\nax.set_xlabel('Latitude', fontsize=14)\nax.set_ylabel('Snow depth [m]', fontsize=14)\nax.set_ylim([0, 2])\nax.legend()","key":"YTQasZWjM3"},{"type":"output","id":"zyAfA3wJURmH8TuPwsmwe","data":[],"key":"eaMUyblLMg"}],"key":"sLAB8edHsW"},{"type":"block","kind":"notebook-content","children":[{"type":"paragraph","position":{"start":{"line":1,"column":1},"end":{"line":1,"column":1}},"children":[{"type":"text","value":"We can also calculate the difference in snow depth between ICESat-2 and UAF, then make a spatial plot using ","position":{"start":{"line":1,"column":1},"end":{"line":1,"column":1}},"key":"QxolMDBu5j"},{"type":"inlineCode","value":"geopandas.explore()","position":{"start":{"line":1,"column":1},"end":{"line":1,"column":1}},"key":"NS3Y4h3V8W"},{"type":"text","value":".","position":{"start":{"line":1,"column":1},"end":{"line":1,"column":1}},"key":"cqOxkiFVHX"}],"key":"FBLCm7dIuX"}],"key":"X7mmXIvT0S"},{"type":"block","kind":"notebook-code","children":[{"type":"code","lang":"python","executable":true,"value":"# Calculate snow depth bias\natl06sr_uaf_gdf['snow_depth_residual'] = atl06sr_uaf_gdf['is2_snow_depth'] - atl06sr_uaf_gdf['lidar_snow_depth']\n\n# Create a spatial plot of the snow depth bias\natl06sr_uaf_gdf.explore(column='snow_depth_residual', \n                        tiles='Esri.WorldImagery',\n                        cmap='viridis',\n                        vmin=-1.5, vmax=1.5)","key":"D0vFSGdKmc"},{"type":"output","id":"7vzvgRm0YMFBelfmGJLc1","data":[],"key":"FlcLqEKzwC"}],"key":"WPdg8iJDrj"},{"type":"block","kind":"notebook-content","children":[{"type":"paragraph","position":{"start":{"line":1,"column":1},"end":{"line":1,"column":1}},"children":[{"type":"text","value":"If the data looks good, then we can save the final GeoDataFrame as a geoJSON.","position":{"start":{"line":1,"column":1},"end":{"line":1,"column":1}},"key":"hejgxa66OY"}],"key":"nuHBDiMbxB"}],"key":"Nj4U4csSLe"},{"type":"block","kind":"notebook-code","children":[{"type":"code","lang":"python","executable":true,"value":"# Save the GeoDataFrame\natl06sr_uaf_gdf.to_file(f'{path}/is2_uaf_snow-depths.geojson',\n                        driver='GeoJSON')","key":"nU6xkpuWVw"},{"type":"output","id":"IIqz8AaaQqAUUlI4iEUf7","data":[],"key":"V93Dd2F6Jj"}],"key":"eegsN4bN3r"}],"key":"UB5BeIPxVy"},"references":{"cite":{"order":[],"data":{}}},"footer":{"navigation":{"prev":{"title":"Terrestrial Laser Scanning","url":"/notebooks/tls-data-access","group":"Observations"},"next":{"title":"SNOTEL Data Access","url":"/notebooks/snotel-data-access","group":"Observations"}}},"domain":"http://localhost:3000"}